Workbook
Name add_5: #REF!
Name Adv_Strategic_Pillars: #REF!
Name Advantages: #REF!
Name Alignment_With_Key_Nike_Objectives__Next_Strategic_Pillars: #REF!
Name Alignment_With_Key_Nike_Objectives_Next__Strategic_Pillars: #REF!
Name Alignment_With_Next__Strategic_Pillars: #REF!
Name AlignmentWithNext_StrategicPillars: #REF!
Name Capital_Expenditure: #REF!
Name Capital_Expenditures: #REF!
Name Cost_of_Goods_Sold: #REF!
Name Costs: 'Costs_L1 Drop Down'!$A$2:$A$6
Name Date: #REF!
Name Direct: #REF!
Name Direct___Indirect: #REF!
Name Engagement: #REF!
Name Expenses: #REF!
Name Increase_in_Average_Transaction_Value: #REF!
Name Increase_in_Conversion: #REF!
Name Increase_in_Foot_Traffic: #REF!
Name Interest: #REF!
Name Name: #REF!
Name number: #REF!
Name Operating_Expenses: #REF!
Name Revenue: 'Rev_L1 Drop Down'!$A$2:$A$4
Name Revenue_Uplift: #REF!
Name Risks: #REF!
Name Scenario_Toggle: 'Scenario Planning_Drop Down'!$A$2:$A$4
Name Scenario_Toggles: 'Scenario Planning_Drop Down'!$A$2:$A$4
Name Strategic_Pillars: #REF!
Name Sub_Levers: #REF!
Name Taxes: #REF!
Name Timeline: #REF!
Name Transition: #REF!
Name Transition_Scaling: #REF!

Sheet 0. Overview & Table of Contents
D2: Liberata: Market Sizing and Financial Projections
D4: 1. Table of Contents breaks down how the Excel file is laid out
C11: 1. Table of Contents:
C13: Section | D13: Index | E13: Description
C14: Instructions & Definitions | D14: 1 | E14: Instructions for how to view and navigate the file in addition to explaining how to adjust inputs and assumptions.
C15: Control Panel | D15: 2 | E15: Provides inputs and assumptions used across the market sizing and financial projections, which can be modified and adjusted, per 1. Instructions & Definitions
C16: Market Sizing Summary | D16: 3 | E16: Provides a high level overview of Total Addressable Market, Serviceable Addressable Market, and Serviceable Obtainable Market across relevant sectors
C17: Market Sizing Calculations | D17: 3.1 | E17: Provides details on methodologies and calculations for market sizing across sectors
C18: Revenue Model Summary | D18: 4 | E18: Provides a high level overview of revenue and cost projections for years 1-10
C19: Revenue & Cost Breakdown | D19: 4.1 | E19: Provides a deeper breakdown of estimates YoY of revenues and costs
C22: 45962

Sheet 1. Instructions & Definitions
D2: Market Sizing and Finanical Projections: Instructions & Definitions
D4: 1. To View & Navigate the File The order in which the viewer should click through the file
D5: 2. To Adjust Inputs and Assumptions Description on how the viewer can adjust the numbers/figures
D6: 3. Important Definitions/Descriptions Explanations on the meaning/importance of various terms/figures used throughout the file
C11: 1.To View & Navigate the File:
C12: 1. After reviewing 1.0 Overview & Table of Contents, review this sheet to understand how to navigate the file
C13: 2. To adjust inputs to both the market sizing and financial projections, proceed to 2. Control Panel to make adjustments to assumptions
C14: 2. Proceed to 3. Market Sizing Summary and 4. Financial Projection Summary to see the high-level overview on the modeling for Liberata
C15: 3. Continue to 3.1 Market Sizing Breakdown to understand specific methodologies used to calculate TAM, SAM, and SOM across relevant markets
C16: 4. Proceed to the 4.1 Revenue & Cost Breakdown to understand initial revenue and cost projections for years 1-10
C18: 2. To Adjust Inputs and Assumptions:
C19: 1. Whenever a blue box saying "Dropdown adjustment" appears, click on the dropdown and choose one of the values to affect the outputs of the sheet
C20: 2. General Rule of Thumb: All numbers in blue in Control Panel are assumptions that can be changed as deemed fit - without breaking the model
C22: 3. Important Definitions/Descriptions:
C23: Word/Value | D23: Sections Included | E23: Definition
C24: Low | D24: 4.0 Financial Projection Summary | E24: Provides a rough sensitivity analysis on revenues and costs, providing a range for expectations
C25: Moderate
C26: High
C27: R1/R2/R3 University | D27: 2.0 Control Panel, 4.1 Revenue & Cost Breakdown | E27: The Carnegie Classification system categorizes U.S. universities based on research activity, degree offerings, and institutional characteristics—such as R1 (very high research), R2 (high research), and R3 (moderate research)—while non-doctoral U.S. universities and global institutions not covered by this framework are classified separately
C28: Non-Doctoral U.S. University
C29: Other Global Universities
C30: Phase 1 - Seed Development | D30: 4.1 Revenue & Cost Breakdown | E30: Phase 1 – Seed Development: Build and launch the core metrics platform with a small team; Phase 2 – Growth: scale the product, marketing, and grow/consider additional AI capabilities; Phase 3 – Expansion: mature operations, expand globally
C31: Phase 2 - Growth
C32: Phase 3 - Expansion

Sheet 2. Control Panel
D2: Market Sizing and Financial Projections: Control Panel
D4: 1. Control Panel 1 Provides inputs and adjustable assumptions included in the market sizing
D5: 2. Control Panel 2 Provides inputs and adjustable assumptions included in the revenue and cost model
C9: Control Panel 1: Market Sizing | I9: Control Panel 2: Financial Projetions
E10: Modify/adjust figures in bolded blue | L10: Modify/adjust figures in bolded blue
C11: Category | D11: Metric Description | E11: Figure | F11: Used in the market sizing? Y/N | G11: Source | I11: Category | J11: User | K11: Metric Description | L11: Figure | M11: Explanation/Justification/Source | O11: SCENARIO 3--- Cost
C12: Academic Publishing | D12: $ size of the entire global academic publishing market | E12: 25600000000 | F12: Yes | G12: https://marketintelo.com/report/academic-publishing-market | I12: Revenue | J12: General - revenues | K12: % growth YoY in users (all users except universities) | L12: 0.1 | M12: ASSUMPTON | O12: Reduces cost growth to test whether improved operational efficiency can enhance profitability and achieve earlier breakeven without increasing revenue.
D13: entire academic publishing global growht rate CAGR | E13: 0.046 | F13: No | G13: https://marketintelo.com/report/academic-publishing-market | K13: % growth YoY in price (i.e.., user spend for non-universities) on subscription in years 1-3 | L13: 0 | M13: ASSUMPTION
D14: % of the academic journal market Liberata can capture | E14: 0.3 | F14: Yes | G14: ASSUMPTION - capturing half of the market that the top 5 journals currently have (which is around 60%) | K14: % growth YoY in price (i.e.., user spend for non-universities) on subscription in years 4-10 | L14: 0.05 | M14: ASSUMPTION
D15: % of the academic publishing market that the top 5 journals make up (El Selvier, Springer Nature, Wiley, Taylor & Francis, Sage) | E15: =0.16+0.15+0.13+0.1+0.06 -> 0.6 | F15: No | G15: https://www.linkedin.com/pulse/hidden-fortune-academic-publishers-closer-look-industrys-kannan-cmxac/ | K15: Sensitivity analysis - Low projections scenario | L15: 0.75 | M15: ASSUMPTION
D16: Percent of journal revenues coming from corporate subscriptions | E16: 0.17 | F16: Yes | G16: https://firstmonday.org/ojs/index.php/fm/article/view/4370/3685 | K16: Sensitivity analysis - Moderate projections scenario | L16: 1 | M16: ASSUMPTION
D17: Percent of journal revenues coming from advertising | E17: 0.04 | F17: Yes | G17: https://firstmonday.org/ojs/index.php/fm/article/view/4370/3685 | K17: Sensitivity analysis - High projections scenario | L17: 1.25 | M17: ASSUMPTION
D18: Percent of journal revenues coming from membership and personal subscriptions | E18: 0.03 | F18: Yes | G18: https://firstmonday.org/ojs/index.php/fm/article/view/4370/3685 | J18: Universities | K18: Number of universities in year 1 with a Liberata subscription | L18: 15 | M18: ASSUMPTION - requires convincing a reasonable amount to try Liberata on free trial
D19: Percent of journal revenues coming from author side payments | E19: 0.03 | F19: Yes | G19: https://firstmonday.org/ojs/index.php/fm/article/view/4370/3685 | K19: % of universities in years 1 and 2 with a free trial Liberata subscription | L19: 1 | M19: ASSUMPTION - requires convincing a reasonable amount to try Liberata on free trial
D20: Percent of journal revenues coming from university library subscriptions | E20: 0.73 | F20: Yes | G20: https://firstmonday.org/ojs/index.php/fm/article/view/4370/3685 | K20: % of universities in years 3 and beyond with a free trial Liberata subscription | L20: 0 | M20: ASSUMPTION - requires convincing a reasonable amount to try Liberata on free trial
C21: Academic metrics | D21: Average annual spend for academic metrics/bibliometrics per university - R1 | E21: =40000 -> 40000 | F21: Yes | G21: ASSUMPTION - based on Han's insights about the cost of Clarivate and SCOPUS | K21: % growth YoY in universities with a Liberata subscription - year 2 | L21: 1 | M21: ASSUMPTION - Network effects will occur as more users join
D22: Average annual spend on academic metrics/bibliometrics per university - R2 | E22: =0.4*E21 -> 16000 | F22: Yes | G22: ASSUMPTION - take 40% of R1 spend | K22: % growth YoY in universities with a Liberata subscription - years 3-5 | L22: 0.5 | M22: ASSUMPTION - May be more challenging to secure many universities once payment is required and free trials end
D23: Average annual spend on academic metrics/bibliometrics per university - R3 | E23: =0.2*E21 -> 8000 | F23: Yes | G23: ASSUMPTION - take 20% of R1 spend | K23: % growth YoY in universities with a Liberata subscription - years 6-8 | L23: 0.6 | M23: ASSUMPTION - Network effects will occur as more users join
D24: Average annual spend for academic metrics/bibliometrics per university - other | E24: =0.05*E21 -> 2000 | F24: Yes | G24: ASSUMPTION - take 5% of R1 spend | K24: % growth YoY in universities with a Liberata subscription - years 9-10 | L24: 0.5 | M24: ASSUMPTION - Growth will slow as the capturable universities are reached
D25: Average annual spend for academic metrics/bibliometrics per university - global | E25: =0.05*E21 -> 2000 | F25: Yes | G25: ASSUMPTION - take 5% of R1 spend | K25: Price of bundle offered to universities - free trial period | L25: 0 | M25: Free trials for universities to show value of the platform
D26: % of universities paying for academic metrics/bibliometrics - R1 | E26: 0.95 | F26: Yes | G26: ASSUMPTION | K26: Starting price - R1 universities | L26: 200000 | M26: Must price Liberata much less than current journal subscription amounts
D27: % of universities paying for academic metrics/bibliometrics - R2 | E27: 0.8 | F27: Yes | G27: ASSUMPTION | K27: Starting price - R2 universities | L27: =0.9*L26 -> 180000 | M27: R2 university price is 90% of R1 university price
D28: % of universities paying for academic metrics/bibliometrics - R3 | E28: 0.6 | F28: Yes | G28: ASSUMPTION | K28: Starting price - R3 universities | L28: =0.8*L26 -> 160000 | M28: R3 university price is 80% of R1 university price
D29: % of universities paying for academic metrics/bibliometrics - other | E29: 0.5 | F29: Yes | G29: ASSUMPTION | K29: Starting price - non-doctoral U.S. universities | L29: =0.7*L26 -> 140000 | M29: Other U.S. university prices are 70% of R1 university price
D30: % of universities paying for academic metrics/bibliometrics - global | E30: 0.2 | F30: Yes | G30: ASSUMPTION | K30: Starting price - other global universities | L30: =0.6*L26 -> 120000 | M30: Other global university prices are 60% of R1 university price
D31: total # R1 research universities | E31: 187 | F31: Yes | G31: https://carnegieclassifications.acenet.edu/institutions/?inst=&research2025%5B%5D=1 | K31: % growth YoY in price for universities (i.e., university spend) years 1-3 | L31: 0 | M31: Liberata needs to gain market share and show value before increasing prices
D32: total # R2 research universities | E32: 139 | F32: Yes | G32: https://carnegieclassifications.acenet.edu/institutions/?inst=&research2025%5B%5D=2 | K32: % growth YoY in price for universities (i.e., university spend) years 4-10 | L32: 0.05 | M32: Universities will be willing to pay more for Liberata as its value is shown and as network effects occur
D33: total # R3 research universities | E33: 189 | F33: Yes | G33: https://robertkelchen.com/2021/12/16/how-colleges-carnegie-classifications-have-changed-over-time-2/#:~:text=Every%20three%20years%2C%20Indiana%20University's%20Center%20on,doesn't%20hesitate%20to%20share%20their%20opinions%20about | K33: total # R1 research universities | L33: =E31 -> 187 | M33: [DO NOT CHANGE HERE - CHANGE IN MARKET SIZING PANEL]
D34: total # other research producing universities in the US | E34: =E42-SUM(E31:E33) -> 555 | F34: Yes | G34: CALCULATION | K34: total # R2 research universities | L34: =E32 -> 139 | M34: [DO NOT CHANGE HERE - CHANGE IN MARKET SIZING PANEL]
D35: total # other research universities globally | E35: =E45-SUM(E31:E34) -> 5788.9744 | F35: Yes | G35: CALCULATION | K35: total # R3 research universities | L35: =E33 -> 189 | M35: [DO NOT CHANGE HERE - CHANGE IN MARKET SIZING PANEL]
D36: academic metrics growth rate | E36: Unknown | F36: No | K36: total # other research producing universities in the US | L36: =E34 -> 555 | M36: [DO NOT CHANGE HERE - CHANGE IN MARKET SIZING PANEL]
C37: AI Licensing for academic publishing | D37: AI Licensing for Academic Publishing | E37: 381800000 | F37: Yes | G37: https://www.grandviewresearch.com/industry-analysis/ai-datasets-licensing-academic-research-publishing-market-report | K37: total # other research universities globally | L37: =E35 -> 5788.9744 | M37: [DO NOT CHANGE HERE - CHANGE IN MARKET SIZING PANEL]
D38: AI Licensing for Academic Publishing growth rate CAGR | E38: 0.268 | F38: No | G38: https://www.grandviewresearch.com/industry-analysis/ai-datasets-licensing-academic-research-publishing-market-report | J38: Think Tanks/Non-profits | K38: Number of think tanks/non-profits in years 1-5 with a Liberata subscription | L38: 0 | M38: ASSUMPTION - conservative estimation that the focus of BD efforts will be on universities for the first five years
D39: AI Training Dataset Share of entire AI licensing market | E39: 0.324 | F39: Yes | G39: https://www.grandviewresearch.com/industry-analysis/ai-datasets-licensing-academic-research-publishing-market-report | K39: Number of think tanks/non-profits in year 6 with a Liberata subscription | L39: 3000 | M39: ASSUMPTION - there are around 2 million non profits in the US
D40: North america share of revenue for AI licensing market | E40: 0.394 | F40: No | G40: https://www.grandviewresearch.com/industry-analysis/ai-datasets-licensing-academic-research-publishing-market-report | K40: Cost of bundle offered to think tanks/non-profits | L40: 50000 | M40: ASSUMPTION
D41: % of the market Liberata can capture | E41: 0.1 | F41: Yes | G41: ASSUMPTION | J41: Government Organizations | K41: Number of government orgs in years 1-5 with a Liberata subscription | L41: 0 | M41: ASSUMPTION - conservative estimation that the focus of BD efforts will be on universities for the first five years
C42: General | D42: # of research producing instutitions - US based | E42: =115+104+109+742 -> 1070 | F42: Yes | G42: https://nces.ed.gov/programs/digest/d18/tables/dt18_317.40.asp | K42: Number of government orgs in year 6 with a Liberata subscription | L42: 500 | M42: ASSUMPTION
D43: United states share of research publications in 2020 | E43: 0.156 | F43: Yes | G43: https://research-and-innovation.ec.europa.eu/system/files/2022-07/ec_rtd_srip-2022-report-chapter-6.pdf#:~:text=Figure%206.1%2D1:%20World%20share%20of%20scientific%20publications(1)%2C,(2)BRIS:%20Brazil%2C%20Russia%2C%20India%20and%20South%20Africa. | K43: Cost of bundle offered to government organizations | L43: 50000 | M43: ASSUMPTION
D44: # of research producing instutitions - Non-US | E44: =(E42/E43)*(1-E43) -> 5788.9744 | F44: Yes | G44: CALCULATION | J44: Corporations | K44: Number of corporations in years 1-5 with a Liberata subscription | L44: 0 | M44: ASSUMPTION - conservative estimation that the focus of BD efforts will be on universities for the first five years
D45: # of research producing instutitions - Globally | E45: =E42+E44 -> 6858.9744 | F45: Yes | G45: CALCULATION | K45: Number of corporations in year 6 with a Liberata subscription | L45: 500 | M45: ASSUMPTION
C46: EdTech | D46: Academic software market size | E46: 2500000000 | F46: No | G46: https://www.globalinsightservices.com/reports/academic-software-market/ | K46: Cost of bundle offered to corporations | L46: 100000 | M46: ASSUMPTION
D47: Academic software industry growth rate (CAGR) | E47: 0.088 | F47: No | G47: https://www.globalinsightservices.com/reports/academic-software-market/ | J47: Publishing Organizations | K47: Number of publishing organizations in years 1-5 with a Liberata subscription | L47: 0 | M47: ASSUMPTION - conservative estimation that the focus of BD efforts will be on universities for the first five years
K48: Number of publishing organizations in year 6 with a Liberata subscription | L48: 50 | M48: ASSUMPTION
K49: Cost of bundle offered to Publishing organizations | L49: 10000 | M49: ASSUMPTION
J50: Rankings Organizations | K50: Number of rankings organizations in years 1-5 with a Liberata subscription | L50: 0 | M50: ASSUMPTION - conservative estimation that the focus of BD efforts will be on universities for the first five years
K51: Number of rankings organizations in year 6 with a Liberata subscription | L51: 10 | M51: ASSUMPTION
K52: Cost of bundle offered to rankings organizations | L52: 30000 | M52: ASSUMPTION
I53: Costs | J53: General - costs | K53: Annual SG&A % cost increase | L53: 0.12 | M53: ASSUMPTION | N53: COST ADJUSTMENT — SG&A cost growth: 20% → 12%: SG&A cost growth is reduced to reflect more disciplined overhead management and lean administrative scaling. Instead of expanding general and administrative functions in proportion to projected growth, the model assumes tighter cost control and improved operational efficiency. This lowers fixed overhead burden in early years without constraining core business activities.
K54: Annual cloud infrastructure % cost increase | L54: 0.1 | M54: ASSUMPTION | N54: COST ADJUSTMENT — Cloud infrastructure cost growth: 15% → 10%: Cloud infrastructure cost growth is reduced to reflect improved technical efficiency and better resource utilization. The model assumes that infrastructure scaling benefits from optimization and economies of scale, allowing the platform to support growth without proportional increases in cloud spending.
K55: Annual salary & wages & cost increase | L55: 0.05 | M55: ASSUMPTION
K56: Annual marketing & outreach % cost increase | L56: 0.1 | M56: ASSUMPTION | N56: COST ADJUSTMENT — Marketing & outreach cost growth: 15% → 10%: Marketing cost growth is reduced to reflect more targeted and efficient customer acquisition strategies. Instead of scaling outreach spend aggressively, the model assumes improved return on marketing investment through better segmentation, institutional targeting, and relationship-driven engagement.
J57: Phase 1 costs | K57: Number of front end engineers hired | L57: 3 | M57: ASSUMPTION
K58: Number of back end engineers hired | L58: 4 | M58: ASSUMPTION | N58: COST ADJUSTMENT — Back-end engineers hired: 6 → 4: Back-end hiring is reduced to reflect a leaner initial engineering team and more efficient allocation of development resources. The model assumes that core platform functionality can be supported with a smaller team in early stages, with additional hiring delayed until demand is more certain.
K59: Number of infrastructure/devops personnel hired | L59: 2 | M59: ASSUMPTION
K60: Number of cybersecurity personnel hired | L60: 1 | M60: ASSUMPTION
K61: Number of full stack engineers hired | L61: 1 | M61: ASSUMPTION
K62: Number of technical managers hired | L62: 1 | M62: ASSUMPTION
K63: Number of marketing and finance personnel hired | L63: 2 | M63: ASSUMPTION | N63: COST ADJUSTMENT — Marketing and finance personnel hired: 3 → 2: Business-side headcount is reduced to reflect a lean go-to-market and operational structure in early stages. The model assumes that initial outreach and administrative functions can be managed by a smaller team, supported by more focused institutional targeting and founder-led engagement.
K64: Number of executive team members | L64: 6 | M64: ASSUMPTION
K65: Front end engineer annual cost | L65: 130000 | M65: ASSUMPTION
K66: Back engineer annual cost | L66: 140000 | M66: ASSUMPTION
K67: Infrastructure/Devops personnel annual cost | L67: 150000 | M67: ASSUMPTION
K68: Cybersecurity personnel annual cost | L68: 140000 | M68: ASSUMPTION
K69: Full stack engineer annual cost | L69: 140000 | M69: ASSUMPTION
K70: Technical manager annual cost | L70: 170000 | M70: ASSUMPTION
K71: Marketing personnel annual cost | L71: 90000 | M71: ASSUMPTION
K72: Executive team member annual cost | L72: 100000 | M72: ASSUMPTION - this may need to be adjusted as time goes on
K73: Cloud Infrastructure annual costs | L73: 25000 | M73: ASSUMPTION
K74: SG&A annual costs | L74: 50000 | M74: ASSUMPTION
K75: Marketing & outreach annual costs | L75: 100000 | M75: ASSUMPTION
J76: Phase 2 costs | K76: Additional data engineers hired | L76: 3 | M76: ASSUMPTION | N76: COST ADJUSTMENT — Additional data engineers (Phase 2): 5 → 3: Phase 2 engineering expansion is scaled back to delay large increases in technical headcount. The model assumes that product development can continue with a smaller team while prioritizing core features, reducing early-stage salary costs and improving capital efficiency.
K77: Data engineer annual cost | L77: =AVERAGE(L65:L69) -> 140000 | M77: CALCULATION - averaged cost of other engineers
K78: Marketing personnel annual % growth rate | L78: 0.05 | M78: ASSUMPTION
K79: Other business functions personnel hired | L79: 6 | M79: ASSUMPTION - includes accounting, finance, operations, etc | N79: COST ADJUSTMENT — Other business personnel (Phase 2): 10 → 6: Expansion of business functions such as operations and finance is moderated to reflect a more gradual organizational build-out. Hiring is aligned more closely with realized growth rather than projected scale, reducing unnecessary early-stage overhead.
K80: Other business functions annual cost | L80: 120000 | M80: ASSUMPTION
K81: Other business functions annual % growth rate | L81: 0.1 | M81: ASSUMPTION
K82: Leadership new annual cost (new annual cost after pay raise from Phase 1) | L82: 120000 | M82: ASSUMPTION
K83: Leadership new annual % growth rate | L83: 0.08 | M83: ASSUMPTION
K84: AI training costs | L84: 25000 | M84: ASSUMPTION
K85: AI training annual % cost increase | L85: 0.15 | M85: ASSUMPTION
J86: Phase 3 costs | K86: Additional data engineers hired | L86: 12 | M86: ASSUMPTION | N86: COST ADJUSTMENT — Additional data engineers (Phase 3): 20 → 12: Late-stage engineering expansion is reduced to reflect more efficient scaling of technical resources. The model assumes that improvements in tooling, infrastructure, and development processes allow the platform to support growth with a smaller incremental team, lowering long-term cost escalation.
K87: Data engineer annual cost | L87: =L77 -> 140000 | M87: CALCULATION - averaged cost of other engineers
K88: Office and equipment costs | L88: 500000 | M88: ASSUMPTION

Sheet 3. Market Sizing Summary
D2: Market Sizing Summary
D4: 1. Market Sizing Summary Summarized findings from 3.1 Market Sizing Breakdown
C9: Market Sizing Summary
C11: Market | D11: Industry Growth Rate (CAGR) | E11: TAM | F11: SAM | G11: SOM
C12: Academic Publishing | D12: ='2. Control Panel'!E13 -> 0.046 | E12: ='3.1 Market Sizing Breakdown'!E16 -> 25600000000 | F12: ='3.1 Market Sizing Breakdown'!E17 -> 24832000000 | G12: ='3.1 Market Sizing Breakdown'!E18 -> 7449600000
C13: Academic Metrics | D13: ='2. Control Panel'!E36 -> Unknown | E13: ='3.1 Market Sizing Breakdown'!G25 -> 12662990 | F13: ='3.1 Market Sizing Breakdown'!G30 -> 12662990 | G13: ='3.1 Market Sizing Breakdown'!G31 -> 12662990
C14: AI Licensing | D14: ='2. Control Panel'!E38 -> 0.268 | E14: ='3.1 Market Sizing Breakdown'!E38 -> 381800000 | F14: ='3.1 Market Sizing Breakdown'!E39 -> 123703200 | G14: ='3.1 Market Sizing Breakdown'!E40 -> 12370320
C15: TOTALS | E15: =SUM(E12:E14) -> 2.5994463e+10 | F15: =SUM(F12:F14) -> 2.4968366e+10 | G15: =SUM(G12:G14) -> 7.4746333e+09
C17: Note: Although not used in market sizing calculations, the industry CAGR for academic/educational software is 8.8%

Sheet 3.1 Market Sizing Breakdown
D2: Market Sizing Breakdown
D4: 1. Assumptions Details key decision points affecting the model
D5: 2. Market Sizing by Sector Breaks down market sizing for three relevant sectors
C8: Assumptions
B9: 1 | C9: Universities conducting more research are 1) spending more and 2) more likely to spend money on academic metrics
B10: 2 | C10: Liberata's patent and ability to maintain superior metrics enables it to capture the entire academic metrics market
B11: 3 | C11: Liberata will be able to capture roughly a tenth of the AI licensing for academic publishing market
C13: 1. Academic Publishing
C15: Level | D15: Method Description | E15: Total Figure
C16: Total Addressable Market (TAM) | D16: Based on global market size estimates from Market Intelo covering the broader academic publishing | E16: ='2. Control Panel'!E12 -> 25600000000
C17: Serviceable Addressable Market (SAM) | D17: Narrows this down to the segments Liberata can realistically target—subscriptions from university libraries, corporations, and individual users in addition to advertising—while excluding author-side APC article processing payments that don’t fit Liberata’s model Method: TAM x relevant category percentages (e.g., subscriptions but NOT article processing charges) | E17: ='2. Control Panel'!E12*('2. Control Panel'!E16+'2. Control Panel'!E17+'2. Control Panel'!E18+'2. Control Panel'!E20) -> 24832000000
C18: Serviceable Obtainable Market (SOM) | D18: Reflects an assumed percentage of the market that Liberata can realistically capture as the industry gradually shifts from view-based to metric-based incentives, recognizing that part of the market will likely stay tied to legacy journal systems | E18: =E17*'2. Control Panel'!E14 -> 7449600000
C22: 2. Academic Metrics
C24: Level | D24: Method Description | E24: Breakdown of categories | F24: Broken down figure | G24: Total Figure
C25: Total Addressable Market (TAM) | D25: Calculated by multiplying the number of research-producing institutions globally—broken down by Carnegie Classifiers (R1, R2, R3, and other U.S. or international equivalents)—by their estimated annual spend on academic metrics, then adjusting for each group’s likelihood of paying for such tools Method: Number of each type of university x spend based on the type of university x percentage likelihood of each type of university to spend on academic metrics | E25: R1 University | F25: ='2. Control Panel'!E21*'2. Control Panel'!E26*'2. Control Panel'!E31 -> 7106000 | G25: =SUM(F25:F29) -> 12662990
E26: R2 University | F26: ='2. Control Panel'!E22*'2. Control Panel'!E27*'2. Control Panel'!E32 -> 1779200
E27: R3 University | F27: ='2. Control Panel'!E23*'2. Control Panel'!E28*'2. Control Panel'!E33 -> 907200
E28: Other US non-doctoral instutiton | F28: ='2. Control Panel'!E24*'2. Control Panel'!E29*'2. Control Panel'!E34 -> 555000
E29: Other global university | F29: ='2. Control Panel'!E25*'2. Control Panel'!E30*'2. Control Panel'!E35 -> 2315589.7
C30: Serviceable Addressable Market (SAM) | D30: Assumes Liberata’s superior academic metrics position it to capture the entire academic metrics segment globally | G30: =G25 -> 12662990
C31: Serviceable Obtainable Market (SOM) | D31: Reflects Liberata’s ability to scale as a platform and maintain that market over time, supported by its patent and sustained competitive advantage | G31: =G30 -> 12662990
C35: 3. AI Licensing
C37: Level | D37: Method Description | E37: Total Figure
C38: Total Addressable Market (TAM) | D38: Based on global market size data from Grandview Research for the AI datasets and licensing market | E38: ='2. Control Panel'!E37 -> 381800000
C39: Serviceable Addressable Market (SAM) | D39: Represents the portion of the market driven by LLM producers purchasing training data, calculated as 32.4% of the total per Grandview Research | E39: ='2. Control Panel'!E37*'2. Control Panel'!E39 -> 123703200
C40: Serviceable Obtainable Market (SOM) | D40: Reflects the share Liberata can realistically capture as its user base and dataset quality grow—driven by improved research data and replication incentives—calculated by applying an assumed market capture rate to the SAM | E40: ='2. Control Panel'!E37*'2. Control Panel'!E39*'2. Control Panel'!E41 -> 12370320

Sheet 4. Financial Projection Summary
D2: Financial Projection Summary
D4: 1. Revenue Projections Breaks down revenue expectations across various users
D5: 2. Cost Projections Breaks down costs across OpEx and CapEx
D6: 3. Profit Projections Summarizes profit expectations based on revenue and costs
D9: Dropdown adjustment
C10: Sensitivity Analysis - Low/Moderate/High revenue projections | D10: Moderate
C13: Revenue Projections
C15: User Types | D15: User | E15: 2026 | F15: 2027 | G15: 2028 | H15: 2029 | I15: 2030 | J15: 2031 | K15: 2032 | L15: 2033 | M15: 2034 | N15: 2035
C16: Institutions | D16: Universities | E16: {=_xlfn.IFS($D$10="Low",'2. Control Panel'!$L$15*'4.1 Revenue & Cost Breakdown'!D57,'4. Financial Projection Summary'!$D$10="Moderate",'2. Control Panel'!$L$16*'4.1 Revenue & Cost Breakdown'!D57,'4. Financial Projection Summary'!$D$10="High",'2. Control Panel'!$L$17*'4.1 Revenue & Cost Breakdown'!D57)} -> 0 | F16: {=_xlfn.IFS($D$10="Low",'2. Control Panel'!$L$15*'4.1 Revenue & Cost Breakdown'!E57,'4. Financial Projection Summary'!$D$10="Moderate",'2. Control Panel'!$L$16*'4.1 Revenue & Cost Breakdown'!E57,'4. Financial Projection Summary'!$D$10="High",'2. Control Panel'!$L$17*'4.1 Revenue & Cost Breakdown'!E57)} -> 3000000 | G16: {=_xlfn.IFS($D$10="Low",'2. Control Panel'!$L$15*'4.1 Revenue & Cost Breakdown'!F57,'4. Financial Projection Summary'!$D$10="Moderate",'2. Control Panel'!$L$16*'4.1 Revenue & Cost Breakdown'!F57,'4. Financial Projection Summary'!$D$10="High",'2. Control Panel'!$L$17*'4.1 Revenue & Cost Breakdown'!F57)} -> 9000000 | H16: {=_xlfn.IFS($D$10="Low",'2. Control Panel'!$L$15*'4.1 Revenue & Cost Breakdown'!G57,'4. Financial Projection Summary'!$D$10="Moderate",'2. Control Panel'!$L$16*'4.1 Revenue & Cost Breakdown'!G57,'4. Financial Projection Summary'!$D$10="High",'2. Control Panel'!$L$17*'4.1 Revenue & Cost Breakdown'!G57)} -> 14175000 | I16: {=_xlfn.IFS($D$10="Low",'2. Control Panel'!$L$15*'4.1 Revenue & Cost Breakdown'!H57,'4. Financial Projection Summary'!$D$10="Moderate",'2. Control Panel'!$L$16*'4.1 Revenue & Cost Breakdown'!H57,'4. Financial Projection Summary'!$D$10="High",'2. Control Panel'!$L$17*'4.1 Revenue & Cost Breakdown'!H57)} -> 22325625 | J16: {=_xlfn.IFS($D$10="Low",'2. Control Panel'!$L$15*'4.1 Revenue & Cost Breakdown'!I57,'4. Financial Projection Summary'!$D$10="Moderate",'2. Control Panel'!$L$16*'4.1 Revenue & Cost Breakdown'!I57,'4. Financial Projection Summary'!$D$10="High",'2. Control Panel'!$L$17*'4.1 Revenue & Cost Breakdown'!I57)} -> 37507050 | K16: {=_xlfn.IFS($D$10="Low",'2. Control Panel'!$L$15*'4.1 Revenue & Cost Breakdown'!J57,'4. Financial Projection Summary'!$D$10="Moderate",'2. Control Panel'!$L$16*'4.1 Revenue & Cost Breakdown'!J57,'4. Financial Projection Summary'!$D$10="High",'2. Control Panel'!$L$17*'4.1 Revenue & Cost Breakdown'!J57)} -> 61256653 | L16: {=_xlfn.IFS($D$10="Low",'2. Control Panel'!$L$15*'4.1 Revenue & Cost Breakdown'!K57,'4. Financial Projection Summary'!$D$10="Moderate",'2. Control Panel'!$L$16*'4.1 Revenue & Cost Breakdown'!K57,'4. Financial Projection Summary'!$D$10="High",'2. Control Panel'!$L$17*'4.1 Revenue & Cost Breakdown'!K57)} -> 97782567 | ... N16: {=_xlfn.IFS($D$10="Low",'2. Control Panel'!$L$15*'4.1 Revenue & Cost Breakdown'!M57,'4. Financial Projection Summary'!$D$10="Moderate",'2. Control Panel'!$L$16*'4.1 Revenue & Cost Breakdown'!M57,'4. Financial Projection Summary'!$D$10="High",'2. Control Panel'!$L$17*'4.1 Revenue & Cost Breakdown'!M57)} -> 2.1274908e+08
D17: Think Tanks/Non-Profits | E17: {=_xlfn.IFS($D$10="Low",'2. Control Panel'!$L$15*'4.1 Revenue & Cost Breakdown'!D67,'4. Financial Projection Summary'!$D$10="Moderate",'2. Control Panel'!$L$16*'4.1 Revenue & Cost Breakdown'!D67,'4. Financial Projection Summary'!$D$10="High",'2. Control Panel'!$L$17*'4.1 Revenue & Cost Breakdown'!D67)} -> 0 | F17: {=_xlfn.IFS($D$10="Low",'2. Control Panel'!$L$15*'4.1 Revenue & Cost Breakdown'!E67,'4. Financial Projection Summary'!$D$10="Moderate",'2. Control Panel'!$L$16*'4.1 Revenue & Cost Breakdown'!E67,'4. Financial Projection Summary'!$D$10="High",'2. Control Panel'!$L$17*'4.1 Revenue & Cost Breakdown'!E67)} -> 0 | G17: {=_xlfn.IFS($D$10="Low",'2. Control Panel'!$L$15*'4.1 Revenue & Cost Breakdown'!F67,'4. Financial Projection Summary'!$D$10="Moderate",'2. Control Panel'!$L$16*'4.1 Revenue & Cost Breakdown'!F67,'4. Financial Projection Summary'!$D$10="High",'2. Control Panel'!$L$17*'4.1 Revenue & Cost Breakdown'!F67)} -> 0 | H17: {=_xlfn.IFS($D$10="Low",'2. Control Panel'!$L$15*'4.1 Revenue & Cost Breakdown'!G67,'4. Financial Projection Summary'!$D$10="Moderate",'2. Control Panel'!$L$16*'4.1 Revenue & Cost Breakdown'!G67,'4. Financial Projection Summary'!$D$10="High",'2. Control Panel'!$L$17*'4.1 Revenue & Cost Breakdown'!G67)} -> 0 | I17: {=_xlfn.IFS($D$10="Low",'2. Control Panel'!$L$15*'4.1 Revenue & Cost Breakdown'!H67,'4. Financial Projection Summary'!$D$10="Moderate",'2. Control Panel'!$L$16*'4.1 Revenue & Cost Breakdown'!H67,'4. Financial Projection Summary'!$D$10="High",'2. Control Panel'!$L$17*'4.1 Revenue & Cost Breakdown'!H67)} -> 0 | J17: {=_xlfn.IFS($D$10="Low",'2. Control Panel'!$L$15*'4.1 Revenue & Cost Breakdown'!I67,'4. Financial Projection Summary'!$D$10="Moderate",'2. Control Panel'!$L$16*'4.1 Revenue & Cost Breakdown'!I67,'4. Financial Projection Summary'!$D$10="High",'2. Control Panel'!$L$17*'4.1 Revenue & Cost Breakdown'!I67)} -> 173643750 | K17: {=_xlfn.IFS($D$10="Low",'2. Control Panel'!$L$15*'4.1 Revenue & Cost Breakdown'!J67,'4. Financial Projection Summary'!$D$10="Moderate",'2. Control Panel'!$L$16*'4.1 Revenue & Cost Breakdown'!J67,'4. Financial Projection Summary'!$D$10="High",'2. Control Panel'!$L$17*'4.1 Revenue & Cost Breakdown'!J67)} -> 2.0055853e+08 | L17: {=_xlfn.IFS($D$10="Low",'2. Control Panel'!$L$15*'4.1 Revenue & Cost Breakdown'!K67,'4. Financial Projection Summary'!$D$10="Moderate",'2. Control Panel'!$L$16*'4.1 Revenue & Cost Breakdown'!K67,'4. Financial Projection Summary'!$D$10="High",'2. Control Panel'!$L$17*'4.1 Revenue & Cost Breakdown'!K67)} -> 2.316451e+08 | ... N17: {=_xlfn.IFS($D$10="Low",'2. Control Panel'!$L$15*'4.1 Revenue & Cost Breakdown'!M67,'4. Financial Projection Summary'!$D$10="Moderate",'2. Control Panel'!$L$16*'4.1 Revenue & Cost Breakdown'!M67,'4. Financial Projection Summary'!$D$10="High",'2. Control Panel'!$L$17*'4.1 Revenue & Cost Breakdown'!M67)} -> 3.0902036e+08
D18: Government | E18: {=_xlfn.IFS($D$10="Low",'2. Control Panel'!$L$15*'4.1 Revenue & Cost Breakdown'!D77,'4. Financial Projection Summary'!$D$10="Moderate",'2. Control Panel'!$L$16*'4.1 Revenue & Cost Breakdown'!D77,'4. Financial Projection Summary'!$D$10="High",'2. Control Panel'!$L$17*'4.1 Revenue & Cost Breakdown'!D77)} -> 0 | F18: {=_xlfn.IFS($D$10="Low",'2. Control Panel'!$L$15*'4.1 Revenue & Cost Breakdown'!E77,'4. Financial Projection Summary'!$D$10="Moderate",'2. Control Panel'!$L$16*'4.1 Revenue & Cost Breakdown'!E77,'4. Financial Projection Summary'!$D$10="High",'2. Control Panel'!$L$17*'4.1 Revenue & Cost Breakdown'!E77)} -> 0 | G18: {=_xlfn.IFS($D$10="Low",'2. Control Panel'!$L$15*'4.1 Revenue & Cost Breakdown'!F77,'4. Financial Projection Summary'!$D$10="Moderate",'2. Control Panel'!$L$16*'4.1 Revenue & Cost Breakdown'!F77,'4. Financial Projection Summary'!$D$10="High",'2. Control Panel'!$L$17*'4.1 Revenue & Cost Breakdown'!F77)} -> 0 | H18: {=_xlfn.IFS($D$10="Low",'2. Control Panel'!$L$15*'4.1 Revenue & Cost Breakdown'!G77,'4. Financial Projection Summary'!$D$10="Moderate",'2. Control Panel'!$L$16*'4.1 Revenue & Cost Breakdown'!G77,'4. Financial Projection Summary'!$D$10="High",'2. Control Panel'!$L$17*'4.1 Revenue & Cost Breakdown'!G77)} -> 0 | I18: {=_xlfn.IFS($D$10="Low",'2. Control Panel'!$L$15*'4.1 Revenue & Cost Breakdown'!H77,'4. Financial Projection Summary'!$D$10="Moderate",'2. Control Panel'!$L$16*'4.1 Revenue & Cost Breakdown'!H77,'4. Financial Projection Summary'!$D$10="High",'2. Control Panel'!$L$17*'4.1 Revenue & Cost Breakdown'!H77)} -> 0 | J18: {=_xlfn.IFS($D$10="Low",'2. Control Panel'!$L$15*'4.1 Revenue & Cost Breakdown'!I77,'4. Financial Projection Summary'!$D$10="Moderate",'2. Control Panel'!$L$16*'4.1 Revenue & Cost Breakdown'!I77,'4. Financial Projection Summary'!$D$10="High",'2. Control Panel'!$L$17*'4.1 Revenue & Cost Breakdown'!I77)} -> 28940625 | K18: {=_xlfn.IFS($D$10="Low",'2. Control Panel'!$L$15*'4.1 Revenue & Cost Breakdown'!J77,'4. Financial Projection Summary'!$D$10="Moderate",'2. Control Panel'!$L$16*'4.1 Revenue & Cost Breakdown'!J77,'4. Financial Projection Summary'!$D$10="High",'2. Control Panel'!$L$17*'4.1 Revenue & Cost Breakdown'!J77)} -> 33426422 | L18: {=_xlfn.IFS($D$10="Low",'2. Control Panel'!$L$15*'4.1 Revenue & Cost Breakdown'!K77,'4. Financial Projection Summary'!$D$10="Moderate",'2. Control Panel'!$L$16*'4.1 Revenue & Cost Breakdown'!K77,'4. Financial Projection Summary'!$D$10="High",'2. Control Panel'!$L$17*'4.1 Revenue & Cost Breakdown'!K77)} -> 38607517 | ... N18: {=_xlfn.IFS($D$10="Low",'2. Control Panel'!$L$15*'4.1 Revenue & Cost Breakdown'!M77,'4. Financial Projection Summary'!$D$10="Moderate",'2. Control Panel'!$L$16*'4.1 Revenue & Cost Breakdown'!M77,'4. Financial Projection Summary'!$D$10="High",'2. Control Panel'!$L$17*'4.1 Revenue & Cost Breakdown'!M77)} -> 51503393
D19: Instutions - Totals | E19: =SUM(E16:E18) -> 0 | F19: =SUM(F16:F18) -> 3000000 | G19: =SUM(G16:G18) -> 9000000 | H19: =SUM(H16:H18) -> 14175000 | I19: =SUM(I16:I18) -> 22325625 | J19: =SUM(J16:J18) -> 240091425 | K19: =SUM(K16:K18) -> 2.9524161e+08 | L19: =SUM(L16:L18) -> 3.6803519e+08 | ... N19: =SUM(N16:N18) -> 5.7327283e+08
C20: Private Industry | D20: Corporations | E20: {=_xlfn.IFS($D$10="Low",'2. Control Panel'!$L$15*'4.1 Revenue & Cost Breakdown'!D87,'4. Financial Projection Summary'!$D$10="Moderate",'2. Control Panel'!$L$16*'4.1 Revenue & Cost Breakdown'!D87,'4. Financial Projection Summary'!$D$10="High",'2. Control Panel'!$L$17*'4.1 Revenue & Cost Breakdown'!D87)} -> 0 | F20: {=_xlfn.IFS($D$10="Low",'2. Control Panel'!$L$15*'4.1 Revenue & Cost Breakdown'!E87,'4. Financial Projection Summary'!$D$10="Moderate",'2. Control Panel'!$L$16*'4.1 Revenue & Cost Breakdown'!E87,'4. Financial Projection Summary'!$D$10="High",'2. Control Panel'!$L$17*'4.1 Revenue & Cost Breakdown'!E87)} -> 0 | G20: {=_xlfn.IFS($D$10="Low",'2. Control Panel'!$L$15*'4.1 Revenue & Cost Breakdown'!F87,'4. Financial Projection Summary'!$D$10="Moderate",'2. Control Panel'!$L$16*'4.1 Revenue & Cost Breakdown'!F87,'4. Financial Projection Summary'!$D$10="High",'2. Control Panel'!$L$17*'4.1 Revenue & Cost Breakdown'!F87)} -> 0 | H20: {=_xlfn.IFS($D$10="Low",'2. Control Panel'!$L$15*'4.1 Revenue & Cost Breakdown'!G87,'4. Financial Projection Summary'!$D$10="Moderate",'2. Control Panel'!$L$16*'4.1 Revenue & Cost Breakdown'!G87,'4. Financial Projection Summary'!$D$10="High",'2. Control Panel'!$L$17*'4.1 Revenue & Cost Breakdown'!G87)} -> 0 | I20: {=_xlfn.IFS($D$10="Low",'2. Control Panel'!$L$15*'4.1 Revenue & Cost Breakdown'!H87,'4. Financial Projection Summary'!$D$10="Moderate",'2. Control Panel'!$L$16*'4.1 Revenue & Cost Breakdown'!H87,'4. Financial Projection Summary'!$D$10="High",'2. Control Panel'!$L$17*'4.1 Revenue & Cost Breakdown'!H87)} -> 0 | J20: {=_xlfn.IFS($D$10="Low",'2. Control Panel'!$L$15*'4.1 Revenue & Cost Breakdown'!I87,'4. Financial Projection Summary'!$D$10="Moderate",'2. Control Panel'!$L$16*'4.1 Revenue & Cost Breakdown'!I87,'4. Financial Projection Summary'!$D$10="High",'2. Control Panel'!$L$17*'4.1 Revenue & Cost Breakdown'!I87)} -> 57881250 | K20: {=_xlfn.IFS($D$10="Low",'2. Control Panel'!$L$15*'4.1 Revenue & Cost Breakdown'!J87,'4. Financial Projection Summary'!$D$10="Moderate",'2. Control Panel'!$L$16*'4.1 Revenue & Cost Breakdown'!J87,'4. Financial Projection Summary'!$D$10="High",'2. Control Panel'!$L$17*'4.1 Revenue & Cost Breakdown'!J87)} -> 66852844 | L20: {=_xlfn.IFS($D$10="Low",'2. Control Panel'!$L$15*'4.1 Revenue & Cost Breakdown'!K87,'4. Financial Projection Summary'!$D$10="Moderate",'2. Control Panel'!$L$16*'4.1 Revenue & Cost Breakdown'!K87,'4. Financial Projection Summary'!$D$10="High",'2. Control Panel'!$L$17*'4.1 Revenue & Cost Breakdown'!K87)} -> 77215035 | ... N20: {=_xlfn.IFS($D$10="Low",'2. Control Panel'!$L$15*'4.1 Revenue & Cost Breakdown'!M87,'4. Financial Projection Summary'!$D$10="Moderate",'2. Control Panel'!$L$16*'4.1 Revenue & Cost Breakdown'!M87,'4. Financial Projection Summary'!$D$10="High",'2. Control Panel'!$L$17*'4.1 Revenue & Cost Breakdown'!M87)} -> 1.0300679e+08
D21: Publishing Organizations | E21: {=_xlfn.IFS($D$10="Low",'2. Control Panel'!$L$15*'4.1 Revenue & Cost Breakdown'!D97,'4. Financial Projection Summary'!$D$10="Moderate",'2. Control Panel'!$L$16*'4.1 Revenue & Cost Breakdown'!D97,'4. Financial Projection Summary'!$D$10="High",'2. Control Panel'!$L$17*'4.1 Revenue & Cost Breakdown'!D97)} -> 0 | F21: {=_xlfn.IFS($D$10="Low",'2. Control Panel'!$L$15*'4.1 Revenue & Cost Breakdown'!E97,'4. Financial Projection Summary'!$D$10="Moderate",'2. Control Panel'!$L$16*'4.1 Revenue & Cost Breakdown'!E97,'4. Financial Projection Summary'!$D$10="High",'2. Control Panel'!$L$17*'4.1 Revenue & Cost Breakdown'!E97)} -> 0 | G21: {=_xlfn.IFS($D$10="Low",'2. Control Panel'!$L$15*'4.1 Revenue & Cost Breakdown'!F97,'4. Financial Projection Summary'!$D$10="Moderate",'2. Control Panel'!$L$16*'4.1 Revenue & Cost Breakdown'!F97,'4. Financial Projection Summary'!$D$10="High",'2. Control Panel'!$L$17*'4.1 Revenue & Cost Breakdown'!F97)} -> 0 | H21: {=_xlfn.IFS($D$10="Low",'2. Control Panel'!$L$15*'4.1 Revenue & Cost Breakdown'!G97,'4. Financial Projection Summary'!$D$10="Moderate",'2. Control Panel'!$L$16*'4.1 Revenue & Cost Breakdown'!G97,'4. Financial Projection Summary'!$D$10="High",'2. Control Panel'!$L$17*'4.1 Revenue & Cost Breakdown'!G97)} -> 0 | I21: {=_xlfn.IFS($D$10="Low",'2. Control Panel'!$L$15*'4.1 Revenue & Cost Breakdown'!H97,'4. Financial Projection Summary'!$D$10="Moderate",'2. Control Panel'!$L$16*'4.1 Revenue & Cost Breakdown'!H97,'4. Financial Projection Summary'!$D$10="High",'2. Control Panel'!$L$17*'4.1 Revenue & Cost Breakdown'!H97)} -> 0 | J21: {=_xlfn.IFS($D$10="Low",'2. Control Panel'!$L$15*'4.1 Revenue & Cost Breakdown'!I97,'4. Financial Projection Summary'!$D$10="Moderate",'2. Control Panel'!$L$16*'4.1 Revenue & Cost Breakdown'!I97,'4. Financial Projection Summary'!$D$10="High",'2. Control Panel'!$L$17*'4.1 Revenue & Cost Breakdown'!I97)} -> 578812.5 | K21: {=_xlfn.IFS($D$10="Low",'2. Control Panel'!$L$15*'4.1 Revenue & Cost Breakdown'!J97,'4. Financial Projection Summary'!$D$10="Moderate",'2. Control Panel'!$L$16*'4.1 Revenue & Cost Breakdown'!J97,'4. Financial Projection Summary'!$D$10="High",'2. Control Panel'!$L$17*'4.1 Revenue & Cost Breakdown'!J97)} -> 668528.44 | L21: {=_xlfn.IFS($D$10="Low",'2. Control Panel'!$L$15*'4.1 Revenue & Cost Breakdown'!K97,'4. Financial Projection Summary'!$D$10="Moderate",'2. Control Panel'!$L$16*'4.1 Revenue & Cost Breakdown'!K97,'4. Financial Projection Summary'!$D$10="High",'2. Control Panel'!$L$17*'4.1 Revenue & Cost Breakdown'!K97)} -> 772150.35 | ... N21: {=_xlfn.IFS($D$10="Low",'2. Control Panel'!$L$15*'4.1 Revenue & Cost Breakdown'!M97,'4. Financial Projection Summary'!$D$10="Moderate",'2. Control Panel'!$L$16*'4.1 Revenue & Cost Breakdown'!M97,'4. Financial Projection Summary'!$D$10="High",'2. Control Panel'!$L$17*'4.1 Revenue & Cost Breakdown'!M97)} -> 1030067.9
D22: Rankings Organizations | E22: {=_xlfn.IFS($D$10="Low",'2. Control Panel'!$L$15*'4.1 Revenue & Cost Breakdown'!D107,'4. Financial Projection Summary'!$D$10="Moderate",'2. Control Panel'!$L$16*'4.1 Revenue & Cost Breakdown'!D107,'4. Financial Projection Summary'!$D$10="High",'2. Control Panel'!$L$17*'4.1 Revenue & Cost Breakdown'!D107)} -> 0 | F22: {=_xlfn.IFS($D$10="Low",'2. Control Panel'!$L$15*'4.1 Revenue & Cost Breakdown'!E107,'4. Financial Projection Summary'!$D$10="Moderate",'2. Control Panel'!$L$16*'4.1 Revenue & Cost Breakdown'!E107,'4. Financial Projection Summary'!$D$10="High",'2. Control Panel'!$L$17*'4.1 Revenue & Cost Breakdown'!E107)} -> 0 | G22: {=_xlfn.IFS($D$10="Low",'2. Control Panel'!$L$15*'4.1 Revenue & Cost Breakdown'!F107,'4. Financial Projection Summary'!$D$10="Moderate",'2. Control Panel'!$L$16*'4.1 Revenue & Cost Breakdown'!F107,'4. Financial Projection Summary'!$D$10="High",'2. Control Panel'!$L$17*'4.1 Revenue & Cost Breakdown'!F107)} -> 0 | H22: {=_xlfn.IFS($D$10="Low",'2. Control Panel'!$L$15*'4.1 Revenue & Cost Breakdown'!G107,'4. Financial Projection Summary'!$D$10="Moderate",'2. Control Panel'!$L$16*'4.1 Revenue & Cost Breakdown'!G107,'4. Financial Projection Summary'!$D$10="High",'2. Control Panel'!$L$17*'4.1 Revenue & Cost Breakdown'!G107)} -> 0 | I22: {=_xlfn.IFS($D$10="Low",'2. Control Panel'!$L$15*'4.1 Revenue & Cost Breakdown'!H107,'4. Financial Projection Summary'!$D$10="Moderate",'2. Control Panel'!$L$16*'4.1 Revenue & Cost Breakdown'!H107,'4. Financial Projection Summary'!$D$10="High",'2. Control Panel'!$L$17*'4.1 Revenue & Cost Breakdown'!H107)} -> 0 | J22: {=_xlfn.IFS($D$10="Low",'2. Control Panel'!$L$15*'4.1 Revenue & Cost Breakdown'!I107,'4. Financial Projection Summary'!$D$10="Moderate",'2. Control Panel'!$L$16*'4.1 Revenue & Cost Breakdown'!I107,'4. Financial Projection Summary'!$D$10="High",'2. Control Panel'!$L$17*'4.1 Revenue & Cost Breakdown'!I107)} -> 347287.5 | K22: {=_xlfn.IFS($D$10="Low",'2. Control Panel'!$L$15*'4.1 Revenue & Cost Breakdown'!J107,'4. Financial Projection Summary'!$D$10="Moderate",'2. Control Panel'!$L$16*'4.1 Revenue & Cost Breakdown'!J107,'4. Financial Projection Summary'!$D$10="High",'2. Control Panel'!$L$17*'4.1 Revenue & Cost Breakdown'!J107)} -> 401117.06 | L22: {=_xlfn.IFS($D$10="Low",'2. Control Panel'!$L$15*'4.1 Revenue & Cost Breakdown'!K107,'4. Financial Projection Summary'!$D$10="Moderate",'2. Control Panel'!$L$16*'4.1 Revenue & Cost Breakdown'!K107,'4. Financial Projection Summary'!$D$10="High",'2. Control Panel'!$L$17*'4.1 Revenue & Cost Breakdown'!K107)} -> 463290.21 | ... N22: {=_xlfn.IFS($D$10="Low",'2. Control Panel'!$L$15*'4.1 Revenue & Cost Breakdown'!M107,'4. Financial Projection Summary'!$D$10="Moderate",'2. Control Panel'!$L$16*'4.1 Revenue & Cost Breakdown'!M107,'4. Financial Projection Summary'!$D$10="High",'2. Control Panel'!$L$17*'4.1 Revenue & Cost Breakdown'!M107)} -> 618040.72
D23: Private Industry - Totals | E23: =SUM(E20:E22) -> 0 | F23: =SUM(F20:F22) -> 0 | G23: =SUM(G20:G22) -> 0 | H23: =SUM(H20:H22) -> 0 | I23: =SUM(I20:I22) -> 0 | J23: =SUM(J20:J22) -> 58807350 | K23: =SUM(K20:K22) -> 67922489 | L23: =SUM(L20:L22) -> 78450475 | ... N23: =SUM(N20:N22) -> 1.046549e+08
D24: TOTAL | E24: =SUM(E19,E23) -> 0 | F24: =SUM(F19,F23) -> 3000000 | G24: =SUM(G19,G23) -> 9000000 | H24: =SUM(H19,H23) -> 14175000 | I24: =SUM(I19,I23) -> 22325625 | J24: =SUM(J19,J23) -> 298898775 | K24: =SUM(K19,K23) -> 3.631641e+08 | L24: =SUM(L19,L23) -> 4.4648566e+08 | ... N24: =SUM(N19,N23) -> 6.7792773e+08
D28: Dropdown adjustment
C29: Sensitivity Analysis - Low/Moderate/High cost projections | D29: Moderate
C31: Cost Projections
C33: User Types | E33: 2026 | F33: 2027 | G33: 2028 | H33: 2029 | I33: 2030 | J33: 2031 | K33: 2032 | L33: 2033 | M33: 2034 | N33: 2035
C34: Operating Expenses (OpEx) | D34: Salary & Wages | E34: {=_xlfn.IFS($D$29="Low",'2. Control Panel'!$L$15*SUM('4.1 Revenue & Cost Breakdown'!D120,'4.1 Revenue & Cost Breakdown'!D122,'4.1 Revenue & Cost Breakdown'!D124,'4.1 Revenue & Cost Breakdown'!D126),'4. Financial Projection Summary'!$D$29="Moderate",'2. Control Panel'!$L$16*SUM('4.1 Revenue & Cost Breakdown'!D120,'4.1 Revenue & Cost Breakdown'!D122,'4.1 Revenue & Cost Breakdown'!D124,'4.1 Revenue & Cost Breakdown'!D126),'4. Financial Projection Summary'!$D$29="High",'2. Control Panel'!$L$17*SUM('4.1 Revenue & Cost Breakdown'!D120,'4.1 Revenue & Cost Breakdown'!D122,'4.1 Revenue & Cost Breakdown'!D124,'4.1 Revenue & Cost Breakdown'!D126))} -> 2480000 | F34: {=_xlfn.IFS($D$29="Low",'2. Control Panel'!$L$15*SUM('4.1 Revenue & Cost Breakdown'!E120,'4.1 Revenue & Cost Breakdown'!E122,'4.1 Revenue & Cost Breakdown'!E124,'4.1 Revenue & Cost Breakdown'!E126),'4. Financial Projection Summary'!$D$29="Moderate",'2. Control Panel'!$L$16*SUM('4.1 Revenue & Cost Breakdown'!E120,'4.1 Revenue & Cost Breakdown'!E122,'4.1 Revenue & Cost Breakdown'!E124,'4.1 Revenue & Cost Breakdown'!E126),'4. Financial Projection Summary'!$D$29="High",'2. Control Panel'!$L$17*SUM('4.1 Revenue & Cost Breakdown'!E120,'4.1 Revenue & Cost Breakdown'!E122,'4.1 Revenue & Cost Breakdown'!E124,'4.1 Revenue & Cost Breakdown'!E126))} -> 2613000 | G34: {=_xlfn.IFS($D$29="Low",'2. Control Panel'!$L$15*SUM('4.1 Revenue & Cost Breakdown'!F120,'4.1 Revenue & Cost Breakdown'!F122,'4.1 Revenue & Cost Breakdown'!F124,'4.1 Revenue & Cost Breakdown'!F126),'4. Financial Projection Summary'!$D$29="Moderate",'2. Control Panel'!$L$16*SUM('4.1 Revenue & Cost Breakdown'!F120,'4.1 Revenue & Cost Breakdown'!F122,'4.1 Revenue & Cost Breakdown'!F124,'4.1 Revenue & Cost Breakdown'!F126),'4. Financial Projection Summary'!$D$29="High",'2. Control Panel'!$L$17*SUM('4.1 Revenue & Cost Breakdown'!F120,'4.1 Revenue & Cost Breakdown'!F122,'4.1 Revenue & Cost Breakdown'!F124,'4.1 Revenue & Cost Breakdown'!F126))} -> 3904800 | H34: {=_xlfn.IFS($D$29="Low",'2. Control Panel'!$L$15*SUM('4.1 Revenue & Cost Breakdown'!G120,'4.1 Revenue & Cost Breakdown'!G122,'4.1 Revenue & Cost Breakdown'!G124,'4.1 Revenue & Cost Breakdown'!G126),'4. Financial Projection Summary'!$D$29="Moderate",'2. Control Panel'!$L$16*SUM('4.1 Revenue & Cost Breakdown'!G120,'4.1 Revenue & Cost Breakdown'!G122,'4.1 Revenue & Cost Breakdown'!G124,'4.1 Revenue & Cost Breakdown'!G126),'4. Financial Projection Summary'!$D$29="High",'2. Control Panel'!$L$17*SUM('4.1 Revenue & Cost Breakdown'!G120,'4.1 Revenue & Cost Breakdown'!G122,'4.1 Revenue & Cost Breakdown'!G124,'4.1 Revenue & Cost Breakdown'!G126))} -> 4168530 | I34: {=_xlfn.IFS($D$29="Low",'2. Control Panel'!$L$15*SUM('4.1 Revenue & Cost Breakdown'!H120,'4.1 Revenue & Cost Breakdown'!H122,'4.1 Revenue & Cost Breakdown'!H124,'4.1 Revenue & Cost Breakdown'!H126),'4. Financial Projection Summary'!$D$29="Moderate",'2. Control Panel'!$L$16*SUM('4.1 Revenue & Cost Breakdown'!H120,'4.1 Revenue & Cost Breakdown'!H122,'4.1 Revenue & Cost Breakdown'!H124,'4.1 Revenue & Cost Breakdown'!H126),'4. Financial Projection Summary'!$D$29="High",'2. Control Panel'!$L$17*SUM('4.1 Revenue & Cost Breakdown'!H120,'4.1 Revenue & Cost Breakdown'!H122,'4.1 Revenue & Cost Breakdown'!H124,'4.1 Revenue & Cost Breakdown'!H126))} -> 6349896 | J34: {=_xlfn.IFS($D$29="Low",'2. Control Panel'!$L$15*SUM('4.1 Revenue & Cost Breakdown'!I120,'4.1 Revenue & Cost Breakdown'!I122,'4.1 Revenue & Cost Breakdown'!I124,'4.1 Revenue & Cost Breakdown'!I126),'4. Financial Projection Summary'!$D$29="Moderate",'2. Control Panel'!$L$16*SUM('4.1 Revenue & Cost Breakdown'!I120,'4.1 Revenue & Cost Breakdown'!I122,'4.1 Revenue & Cost Breakdown'!I124,'4.1 Revenue & Cost Breakdown'!I126),'4. Financial Projection Summary'!$D$29="High",'2. Control Panel'!$L$17*SUM('4.1 Revenue & Cost Breakdown'!I120,'4.1 Revenue & Cost Breakdown'!I122,'4.1 Revenue & Cost Breakdown'!I124,'4.1 Revenue & Cost Breakdown'!I126))} -> 6749321.9 | K34: {=_xlfn.IFS($D$29="Low",'2. Control Panel'!$L$15*SUM('4.1 Revenue & Cost Breakdown'!J120,'4.1 Revenue & Cost Breakdown'!J122,'4.1 Revenue & Cost Breakdown'!J124,'4.1 Revenue & Cost Breakdown'!J126),'4. Financial Projection Summary'!$D$29="Moderate",'2. Control Panel'!$L$16*SUM('4.1 Revenue & Cost Breakdown'!J120,'4.1 Revenue & Cost Breakdown'!J122,'4.1 Revenue & Cost Breakdown'!J124,'4.1 Revenue & Cost Breakdown'!J126),'4. Financial Projection Summary'!$D$29="High",'2. Control Panel'!$L$17*SUM('4.1 Revenue & Cost Breakdown'!J120,'4.1 Revenue & Cost Breakdown'!J122,'4.1 Revenue & Cost Breakdown'!J124,'4.1 Revenue & Cost Breakdown'!J126))} -> 7176408.4 | L34: {=_xlfn.IFS($D$29="Low",'2. Control Panel'!$L$15*SUM('4.1 Revenue & Cost Breakdown'!K120,'4.1 Revenue & Cost Breakdown'!K122,'4.1 Revenue & Cost Breakdown'!K124,'4.1 Revenue & Cost Breakdown'!K126),'4. Financial Projection Summary'!$D$29="Moderate",'2. Control Panel'!$L$16*SUM('4.1 Revenue & Cost Breakdown'!K120,'4.1 Revenue & Cost Breakdown'!K122,'4.1 Revenue & Cost Breakdown'!K124,'4.1 Revenue & Cost Breakdown'!K126),'4. Financial Projection Summary'!$D$29="High",'2. Control Panel'!$L$17*SUM('4.1 Revenue & Cost Breakdown'!K120,'4.1 Revenue & Cost Breakdown'!K122,'4.1 Revenue & Cost Breakdown'!K124,'4.1 Revenue & Cost Breakdown'!K126))} -> 7633267 | ... N34: {=_xlfn.IFS($D$29="Low",'2. Control Panel'!$L$15*SUM('4.1 Revenue & Cost Breakdown'!M120,'4.1 Revenue & Cost Breakdown'!M122,'4.1 Revenue & Cost Breakdown'!M124,'4.1 Revenue & Cost Breakdown'!M126),'4. Financial Projection Summary'!$D$29="Moderate",'2. Control Panel'!$L$16*SUM('4.1 Revenue & Cost Breakdown'!M120,'4.1 Revenue & Cost Breakdown'!M122,'4.1 Revenue & Cost Breakdown'!M124,'4.1 Revenue & Cost Breakdown'!M126),'4. Financial Projection Summary'!$D$29="High",'2. Control Panel'!$L$17*SUM('4.1 Revenue & Cost Breakdown'!M120,'4.1 Revenue & Cost Breakdown'!M122,'4.1 Revenue & Cost Breakdown'!M124,'4.1 Revenue & Cost Breakdown'!M126))} -> 8645638.9
D35: Cloud & Compute + AI Training | E35: {=_xlfn.IFS($D$29="Low",'2. Control Panel'!$L$15*SUM('4.1 Revenue & Cost Breakdown'!D128,'4.1 Revenue & Cost Breakdown'!D134),'4. Financial Projection Summary'!$D$29="Moderate",'2. Control Panel'!$L$16*SUM('4.1 Revenue & Cost Breakdown'!D128,'4.1 Revenue & Cost Breakdown'!D134),'4. Financial Projection Summary'!$D$29="High",'2. Control Panel'!$L$17*SUM('4.1 Revenue & Cost Breakdown'!D128,'4.1 Revenue & Cost Breakdown'!D134))} -> 25000 | F35: {=_xlfn.IFS($D$29="Low",'2. Control Panel'!$L$15*SUM('4.1 Revenue & Cost Breakdown'!E128,'4.1 Revenue & Cost Breakdown'!E134),'4. Financial Projection Summary'!$D$29="Moderate",'2. Control Panel'!$L$16*SUM('4.1 Revenue & Cost Breakdown'!E128,'4.1 Revenue & Cost Breakdown'!E134),'4. Financial Projection Summary'!$D$29="High",'2. Control Panel'!$L$17*SUM('4.1 Revenue & Cost Breakdown'!E128,'4.1 Revenue & Cost Breakdown'!E134))} -> 27500 | G35: {=_xlfn.IFS($D$29="Low",'2. Control Panel'!$L$15*SUM('4.1 Revenue & Cost Breakdown'!F128,'4.1 Revenue & Cost Breakdown'!F134),'4. Financial Projection Summary'!$D$29="Moderate",'2. Control Panel'!$L$16*SUM('4.1 Revenue & Cost Breakdown'!F128,'4.1 Revenue & Cost Breakdown'!F134),'4. Financial Projection Summary'!$D$29="High",'2. Control Panel'!$L$17*SUM('4.1 Revenue & Cost Breakdown'!F128,'4.1 Revenue & Cost Breakdown'!F134))} -> 55250 | H35: {=_xlfn.IFS($D$29="Low",'2. Control Panel'!$L$15*SUM('4.1 Revenue & Cost Breakdown'!G128,'4.1 Revenue & Cost Breakdown'!G134),'4. Financial Projection Summary'!$D$29="Moderate",'2. Control Panel'!$L$16*SUM('4.1 Revenue & Cost Breakdown'!G128,'4.1 Revenue & Cost Breakdown'!G134),'4. Financial Projection Summary'!$D$29="High",'2. Control Panel'!$L$17*SUM('4.1 Revenue & Cost Breakdown'!G128,'4.1 Revenue & Cost Breakdown'!G134))} -> 62025 | I35: {=_xlfn.IFS($D$29="Low",'2. Control Panel'!$L$15*SUM('4.1 Revenue & Cost Breakdown'!H128,'4.1 Revenue & Cost Breakdown'!H134),'4. Financial Projection Summary'!$D$29="Moderate",'2. Control Panel'!$L$16*SUM('4.1 Revenue & Cost Breakdown'!H128,'4.1 Revenue & Cost Breakdown'!H134),'4. Financial Projection Summary'!$D$29="High",'2. Control Panel'!$L$17*SUM('4.1 Revenue & Cost Breakdown'!H128,'4.1 Revenue & Cost Breakdown'!H134))} -> 69665 | J35: {=_xlfn.IFS($D$29="Low",'2. Control Panel'!$L$15*SUM('4.1 Revenue & Cost Breakdown'!I128,'4.1 Revenue & Cost Breakdown'!I134),'4. Financial Projection Summary'!$D$29="Moderate",'2. Control Panel'!$L$16*SUM('4.1 Revenue & Cost Breakdown'!I128,'4.1 Revenue & Cost Breakdown'!I134),'4. Financial Projection Summary'!$D$29="High",'2. Control Panel'!$L$17*SUM('4.1 Revenue & Cost Breakdown'!I128,'4.1 Revenue & Cost Breakdown'!I134))} -> 78284.625 | K35: {=_xlfn.IFS($D$29="Low",'2. Control Panel'!$L$15*SUM('4.1 Revenue & Cost Breakdown'!J128,'4.1 Revenue & Cost Breakdown'!J134),'4. Financial Projection Summary'!$D$29="Moderate",'2. Control Panel'!$L$16*SUM('4.1 Revenue & Cost Breakdown'!J128,'4.1 Revenue & Cost Breakdown'!J134),'4. Financial Projection Summary'!$D$29="High",'2. Control Panel'!$L$17*SUM('4.1 Revenue & Cost Breakdown'!J128,'4.1 Revenue & Cost Breakdown'!J134))} -> 88014.181 | L35: {=_xlfn.IFS($D$29="Low",'2. Control Panel'!$L$15*SUM('4.1 Revenue & Cost Breakdown'!K128,'4.1 Revenue & Cost Breakdown'!K134),'4. Financial Projection Summary'!$D$29="Moderate",'2. Control Panel'!$L$16*SUM('4.1 Revenue & Cost Breakdown'!K128,'4.1 Revenue & Cost Breakdown'!K134),'4. Financial Projection Summary'!$D$29="High",'2. Control Panel'!$L$17*SUM('4.1 Revenue & Cost Breakdown'!K128,'4.1 Revenue & Cost Breakdown'!K134))} -> 99001.857 | ... N35: {=_xlfn.IFS($D$29="Low",'2. Control Panel'!$L$15*SUM('4.1 Revenue & Cost Breakdown'!M128,'4.1 Revenue & Cost Breakdown'!M134),'4. Financial Projection Summary'!$D$29="Moderate",'2. Control Panel'!$L$16*SUM('4.1 Revenue & Cost Breakdown'!M128,'4.1 Revenue & Cost Breakdown'!M134),'4. Financial Projection Summary'!$D$29="High",'2. Control Panel'!$L$17*SUM('4.1 Revenue & Cost Breakdown'!M128,'4.1 Revenue & Cost Breakdown'!M134))} -> 125449.19
D36: Marketing & Outreach | E36: {=_xlfn.IFS($D$29="Low",'2. Control Panel'!$L$15*'4.1 Revenue & Cost Breakdown'!D130,'4. Financial Projection Summary'!$D$29="Moderate",'2. Control Panel'!$L$16*'4.1 Revenue & Cost Breakdown'!D130,'4. Financial Projection Summary'!$D$29="High",'2. Control Panel'!$L$17*'4.1 Revenue & Cost Breakdown'!D130)} -> 100000 | F36: {=_xlfn.IFS($D$29="Low",'2. Control Panel'!$L$15*'4.1 Revenue & Cost Breakdown'!E130,'4. Financial Projection Summary'!$D$29="Moderate",'2. Control Panel'!$L$16*'4.1 Revenue & Cost Breakdown'!E130,'4. Financial Projection Summary'!$D$29="High",'2. Control Panel'!$L$17*'4.1 Revenue & Cost Breakdown'!E130)} -> 110000 | G36: {=_xlfn.IFS($D$29="Low",'2. Control Panel'!$L$15*'4.1 Revenue & Cost Breakdown'!F130,'4. Financial Projection Summary'!$D$29="Moderate",'2. Control Panel'!$L$16*'4.1 Revenue & Cost Breakdown'!F130,'4. Financial Projection Summary'!$D$29="High",'2. Control Panel'!$L$17*'4.1 Revenue & Cost Breakdown'!F130)} -> 121000 | H36: {=_xlfn.IFS($D$29="Low",'2. Control Panel'!$L$15*'4.1 Revenue & Cost Breakdown'!G130,'4. Financial Projection Summary'!$D$29="Moderate",'2. Control Panel'!$L$16*'4.1 Revenue & Cost Breakdown'!G130,'4. Financial Projection Summary'!$D$29="High",'2. Control Panel'!$L$17*'4.1 Revenue & Cost Breakdown'!G130)} -> 133100 | I36: {=_xlfn.IFS($D$29="Low",'2. Control Panel'!$L$15*'4.1 Revenue & Cost Breakdown'!H130,'4. Financial Projection Summary'!$D$29="Moderate",'2. Control Panel'!$L$16*'4.1 Revenue & Cost Breakdown'!H130,'4. Financial Projection Summary'!$D$29="High",'2. Control Panel'!$L$17*'4.1 Revenue & Cost Breakdown'!H130)} -> 146410 | J36: {=_xlfn.IFS($D$29="Low",'2. Control Panel'!$L$15*'4.1 Revenue & Cost Breakdown'!I130,'4. Financial Projection Summary'!$D$29="Moderate",'2. Control Panel'!$L$16*'4.1 Revenue & Cost Breakdown'!I130,'4. Financial Projection Summary'!$D$29="High",'2. Control Panel'!$L$17*'4.1 Revenue & Cost Breakdown'!I130)} -> 161051 | K36: {=_xlfn.IFS($D$29="Low",'2. Control Panel'!$L$15*'4.1 Revenue & Cost Breakdown'!J130,'4. Financial Projection Summary'!$D$29="Moderate",'2. Control Panel'!$L$16*'4.1 Revenue & Cost Breakdown'!J130,'4. Financial Projection Summary'!$D$29="High",'2. Control Panel'!$L$17*'4.1 Revenue & Cost Breakdown'!J130)} -> 177156.1 | L36: {=_xlfn.IFS($D$29="Low",'2. Control Panel'!$L$15*'4.1 Revenue & Cost Breakdown'!K130,'4. Financial Projection Summary'!$D$29="Moderate",'2. Control Panel'!$L$16*'4.1 Revenue & Cost Breakdown'!K130,'4. Financial Projection Summary'!$D$29="High",'2. Control Panel'!$L$17*'4.1 Revenue & Cost Breakdown'!K130)} -> 194871.71 | ... N36: {=_xlfn.IFS($D$29="Low",'2. Control Panel'!$L$15*'4.1 Revenue & Cost Breakdown'!M130,'4. Financial Projection Summary'!$D$29="Moderate",'2. Control Panel'!$L$16*'4.1 Revenue & Cost Breakdown'!M130,'4. Financial Projection Summary'!$D$29="High",'2. Control Panel'!$L$17*'4.1 Revenue & Cost Breakdown'!M130)} -> 235794.77
D37: SG&A | E37: {=_xlfn.IFS($D$29="Low",'2. Control Panel'!$L$15*'4.1 Revenue & Cost Breakdown'!D132,'4. Financial Projection Summary'!$D$29="Moderate",'2. Control Panel'!$L$16*'4.1 Revenue & Cost Breakdown'!D132,'4. Financial Projection Summary'!$D$29="High",'2. Control Panel'!$L$17*'4.1 Revenue & Cost Breakdown'!D132)} -> 50000 | F37: {=_xlfn.IFS($D$29="Low",'2. Control Panel'!$L$15*'4.1 Revenue & Cost Breakdown'!E132,'4. Financial Projection Summary'!$D$29="Moderate",'2. Control Panel'!$L$16*'4.1 Revenue & Cost Breakdown'!E132,'4. Financial Projection Summary'!$D$29="High",'2. Control Panel'!$L$17*'4.1 Revenue & Cost Breakdown'!E132)} -> 56000 | G37: {=_xlfn.IFS($D$29="Low",'2. Control Panel'!$L$15*'4.1 Revenue & Cost Breakdown'!F132,'4. Financial Projection Summary'!$D$29="Moderate",'2. Control Panel'!$L$16*'4.1 Revenue & Cost Breakdown'!F132,'4. Financial Projection Summary'!$D$29="High",'2. Control Panel'!$L$17*'4.1 Revenue & Cost Breakdown'!F132)} -> 62720 | H37: {=_xlfn.IFS($D$29="Low",'2. Control Panel'!$L$15*'4.1 Revenue & Cost Breakdown'!G132,'4. Financial Projection Summary'!$D$29="Moderate",'2. Control Panel'!$L$16*'4.1 Revenue & Cost Breakdown'!G132,'4. Financial Projection Summary'!$D$29="High",'2. Control Panel'!$L$17*'4.1 Revenue & Cost Breakdown'!G132)} -> 70246.4 | I37: {=_xlfn.IFS($D$29="Low",'2. Control Panel'!$L$15*'4.1 Revenue & Cost Breakdown'!H132,'4. Financial Projection Summary'!$D$29="Moderate",'2. Control Panel'!$L$16*'4.1 Revenue & Cost Breakdown'!H132,'4. Financial Projection Summary'!$D$29="High",'2. Control Panel'!$L$17*'4.1 Revenue & Cost Breakdown'!H132)} -> 78675.968 | J37: {=_xlfn.IFS($D$29="Low",'2. Control Panel'!$L$15*'4.1 Revenue & Cost Breakdown'!I132,'4. Financial Projection Summary'!$D$29="Moderate",'2. Control Panel'!$L$16*'4.1 Revenue & Cost Breakdown'!I132,'4. Financial Projection Summary'!$D$29="High",'2. Control Panel'!$L$17*'4.1 Revenue & Cost Breakdown'!I132)} -> 88117.084 | K37: {=_xlfn.IFS($D$29="Low",'2. Control Panel'!$L$15*'4.1 Revenue & Cost Breakdown'!J132,'4. Financial Projection Summary'!$D$29="Moderate",'2. Control Panel'!$L$16*'4.1 Revenue & Cost Breakdown'!J132,'4. Financial Projection Summary'!$D$29="High",'2. Control Panel'!$L$17*'4.1 Revenue & Cost Breakdown'!J132)} -> 98691.134 | L37: {=_xlfn.IFS($D$29="Low",'2. Control Panel'!$L$15*'4.1 Revenue & Cost Breakdown'!K132,'4. Financial Projection Summary'!$D$29="Moderate",'2. Control Panel'!$L$16*'4.1 Revenue & Cost Breakdown'!K132,'4. Financial Projection Summary'!$D$29="High",'2. Control Panel'!$L$17*'4.1 Revenue & Cost Breakdown'!K132)} -> 110534.07 | ... N37: {=_xlfn.IFS($D$29="Low",'2. Control Panel'!$L$15*'4.1 Revenue & Cost Breakdown'!M132,'4. Financial Projection Summary'!$D$29="Moderate",'2. Control Panel'!$L$16*'4.1 Revenue & Cost Breakdown'!M132,'4. Financial Projection Summary'!$D$29="High",'2. Control Panel'!$L$17*'4.1 Revenue & Cost Breakdown'!M132)} -> 138653.94
D38: OpEx - Totals | E38: =SUM(E34:E37) -> 2655000 | F38: =SUM(F34:F37) -> 2806500 | G38: =SUM(G34:G37) -> 4143770 | H38: =SUM(H34:H37) -> 4433901.4 | I38: =SUM(I34:I37) -> 6644647 | J38: =SUM(J34:J37) -> 7076774.6 | K38: =SUM(K34:K37) -> 7540269.8 | L38: =SUM(L34:L37) -> 8037674.7 | ... N38: =SUM(N34:N37) -> 9145536.8
C39: Capital Expenditures (CapEx) | D39: Office and other expenditures | E39: {=_xlfn.IFS($D$29="Low",'2. Control Panel'!$L$15*'4.1 Revenue & Cost Breakdown'!D136,'4. Financial Projection Summary'!$D$29="Moderate",'2. Control Panel'!$L$16*'4.1 Revenue & Cost Breakdown'!D136,'4. Financial Projection Summary'!$D$29="High",'2. Control Panel'!$L$17*'4.1 Revenue & Cost Breakdown'!D136)} -> 0 | F39: {=_xlfn.IFS($D$29="Low",'2. Control Panel'!$L$15*'4.1 Revenue & Cost Breakdown'!E136,'4. Financial Projection Summary'!$D$29="Moderate",'2. Control Panel'!$L$16*'4.1 Revenue & Cost Breakdown'!E136,'4. Financial Projection Summary'!$D$29="High",'2. Control Panel'!$L$17*'4.1 Revenue & Cost Breakdown'!E136)} -> 0 | G39: {=_xlfn.IFS($D$29="Low",'2. Control Panel'!$L$15*'4.1 Revenue & Cost Breakdown'!F136,'4. Financial Projection Summary'!$D$29="Moderate",'2. Control Panel'!$L$16*'4.1 Revenue & Cost Breakdown'!F136,'4. Financial Projection Summary'!$D$29="High",'2. Control Panel'!$L$17*'4.1 Revenue & Cost Breakdown'!F136)} -> 0 | H39: {=_xlfn.IFS($D$29="Low",'2. Control Panel'!$L$15*'4.1 Revenue & Cost Breakdown'!G136,'4. Financial Projection Summary'!$D$29="Moderate",'2. Control Panel'!$L$16*'4.1 Revenue & Cost Breakdown'!G136,'4. Financial Projection Summary'!$D$29="High",'2. Control Panel'!$L$17*'4.1 Revenue & Cost Breakdown'!G136)} -> 0 | I39: {=_xlfn.IFS($D$29="Low",'2. Control Panel'!$L$15*'4.1 Revenue & Cost Breakdown'!H136,'4. Financial Projection Summary'!$D$29="Moderate",'2. Control Panel'!$L$16*'4.1 Revenue & Cost Breakdown'!H136,'4. Financial Projection Summary'!$D$29="High",'2. Control Panel'!$L$17*'4.1 Revenue & Cost Breakdown'!H136)} -> 0 | J39: {=_xlfn.IFS($D$29="Low",'2. Control Panel'!$L$15*'4.1 Revenue & Cost Breakdown'!I136,'4. Financial Projection Summary'!$D$29="Moderate",'2. Control Panel'!$L$16*'4.1 Revenue & Cost Breakdown'!I136,'4. Financial Projection Summary'!$D$29="High",'2. Control Panel'!$L$17*'4.1 Revenue & Cost Breakdown'!I136)} -> 0 | K39: {=_xlfn.IFS($D$29="Low",'2. Control Panel'!$L$15*'4.1 Revenue & Cost Breakdown'!J136,'4. Financial Projection Summary'!$D$29="Moderate",'2. Control Panel'!$L$16*'4.1 Revenue & Cost Breakdown'!J136,'4. Financial Projection Summary'!$D$29="High",'2. Control Panel'!$L$17*'4.1 Revenue & Cost Breakdown'!J136)} -> 0 | L39: {=_xlfn.IFS($D$29="Low",'2. Control Panel'!$L$15*'4.1 Revenue & Cost Breakdown'!K136,'4. Financial Projection Summary'!$D$29="Moderate",'2. Control Panel'!$L$16*'4.1 Revenue & Cost Breakdown'!K136,'4. Financial Projection Summary'!$D$29="High",'2. Control Panel'!$L$17*'4.1 Revenue & Cost Breakdown'!K136)} -> 500000 | ... N39: {=_xlfn.IFS($D$29="Low",'2. Control Panel'!$L$15*'4.1 Revenue & Cost Breakdown'!M136,'4. Financial Projection Summary'!$D$29="Moderate",'2. Control Panel'!$L$16*'4.1 Revenue & Cost Breakdown'!M136,'4. Financial Projection Summary'!$D$29="High",'2. Control Panel'!$L$17*'4.1 Revenue & Cost Breakdown'!M136)} -> 500000
D40: CapEx - Totals | E40: =SUM(E39) -> 0 | F40: =SUM(F39) -> 0 | G40: =SUM(G39) -> 0 | H40: =SUM(H39) -> 0 | I40: =SUM(I39) -> 0 | J40: =SUM(J39) -> 0 | K40: =SUM(K39) -> 0 | L40: =SUM(L39) -> 500000 | ... N40: =SUM(N39) -> 500000
D41: TOTALS | E41: =SUM(E38,E40) -> 2655000 | F41: =SUM(F38,F40) -> 2806500 | G41: =SUM(G38,G40) -> 4143770 | H41: =SUM(H38,H40) -> 4433901.4 | I41: =SUM(I38,I40) -> 6644647 | J41: =SUM(J38,J40) -> 7076774.6 | K41: =SUM(K38,K40) -> 7540269.8 | L41: =SUM(L38,L40) -> 8537674.7 | ... N41: =SUM(N38,N40) -> 9645536.8 | O41: COST ADJUSTMENT — Lean scaling and operational efficiency: Early-stage costs decrease from $3.03M to $2.66M (2026) and from $3.21M to $2.81M (2027), driven by reduced hiring and lower SG&A, marketing, and infrastructure cost growth. This reflects a more disciplined, demand-aligned cost structure that significantly lowers early burn without compromising long-term scalability.
C45: Profit Projections
C47: User Types | E47: 2026 | F47: 2027 | G47: 2028 | H47: 2029 | I47: 2030 | J47: 2031 | K47: 2032 | L47: 2033 | M47: 2034 | N47: 2035
C48: Projected Revenues | E48: =E24 -> 0 | F48: =F24 -> 3000000 | G48: =G24 -> 9000000 | H48: =H24 -> 14175000 | I48: =I24 -> 22325625 | J48: =J24 -> 298898775 | K48: =K24 -> 3.631641e+08 | L48: =L24 -> 4.4648566e+08 | ... N48: =N24 -> 6.7792773e+08
C49: Projected Costs | E49: =E41 -> 2655000 | F49: =F41 -> 2806500 | G49: =G41 -> 4143770 | H49: =H41 -> 4433901.4 | I49: =I41 -> 6644647 | J49: =J41 -> 7076774.6 | K49: =K41 -> 7540269.8 | L49: =L41 -> 8537674.7 | ... N49: =N41 -> 9645536.8
C50: EBIT | E50: =E48-E49 -> -2655000 | F50: =F48-F49 -> 193500 | G50: =G48-G49 -> 4856230 | H50: =H48-H49 -> 9741098.6 | I50: =I48-I49 -> 15680978 | J50: =J48-J49 -> 2.91822e+08 | K50: =K48-K49 -> 3.5562383e+08 | L50: =L48-L49 -> 4.3794799e+08 | ... N50: =N48-N49 -> 6.6828219e+08 | O50: EBIT IMPACT — Lean scaling and operational efficiency: EBIT improves from -$209.8K to +$193.5K in 2027, shifting to profitability one year earlier. This is driven by reduced operating costs rather than revenue changes, demonstrating the strong impact of cost efficiency on accelerating breakeven by ~1–2 years.

Sheet 4.1 Revenue & Cost Breakdown
D2: Financial Projection Breakdown
D4: 1. Assumptions Details key decision points affecting the model
D5: 2. Revenues Breaks down revenue expectations across various users
D6: 3. Costs Breaks down costs across OpEx and CapEx
C9: Assumptions
B10: 1 | C10: Individual users are excluded from the model as they represent a negligible share of total revenue
B11: 2 | C11: Revenue is based solely on bundled product offerings, with no income for individual features
B12: 3 | C12: The model focuses exclusively on targeting universities during the first five years
B13: 4 | C13: University adoption growth rates vary over time
B14: 5 | C14: Universities receive one-year free trials, after which all transition to paid subscriptions by year two
B15: 6 | C15: The model excludes additional revenue streams such as advertising, data licensing, or LLM partnerships
B16: 7 | C16: R1 universities are captured first through free trials, followed by sequential adoption by R2 and R3 institutions + non-doctoral U.S. and global universities
B17: 8 | C17: Costs are based on phased rollout of features beginning in 2026, 2028, and 2030 respectively
B18: 9 | C18: AI training operations commence in phase two of implementation
B19: 10 | C19: Capital expenditures (e.g., office) begin midway through phase three (past 2030)
C21: Users
C38: Revenues
C40: User 1 - Universities | D40: Free trial period (note: end of free trial period for universities corresponds with planned feature releases for 2028)
D42: 2026 | E42: 2027 | F42: 2028 | G42: 2029 | H42: 2030 | I42: 2031 | J42: 2032 | K42: 2033 | L42: 2034 | M42: 2035
C43: % growth in universities with Liberata subscriptions | D43: N/A | E43: ='2. Control Panel'!$L$21 -> 1 | F43: ='2. Control Panel'!$L$22 -> 0.5 | G43: ='2. Control Panel'!$L$22 -> 0.5 | H43: ='2. Control Panel'!$L$22 -> 0.5 | I43: ='2. Control Panel'!$L$23 -> 0.6 | J43: ='2. Control Panel'!$L$23 -> 0.6 | K43: ='2. Control Panel'!$L$23 -> 0.6 | L43: ='2. Control Panel'!$L$24 -> 0.5 | M43: ='2. Control Panel'!$L$24 -> 0.5
C44: Total # of universities with a Liberata subscription | D44: ='2. Control Panel'!$L$18 -> 15 | E44: =D44*(1+E43) -> 30 | F44: =E44*(1+F43) -> 45 | G44: =F44*(1+G43) -> 67.5 | H44: =G44*(1+H43) -> 101.25 | I44: =H44*(1+I43) -> 162 | J44: =I44*(1+J43) -> 259.2 | K44: =J44*(1+K43) -> 414.72 | L44: =K44*(1+L43) -> 622.08 | M44: =L44*(1+M43) -> 933.12
C45: Number of universities with one year free trial subscriptions | D45: ='2. Control Panel'!L18*'2. Control Panel'!L19 -> 15 | E45: =(E44-D44)*'2. Control Panel'!L19 -> 15 | F45: =(F44-E44)*'2. Control Panel'!$L$20 -> 0 | G45: =(G44-F44)*'2. Control Panel'!$L$20 -> 0 | H45: =(H44-G44)*'2. Control Panel'!$L$20 -> 0 | I45: =(I44-H44)*'2. Control Panel'!$L$20 -> 0 | J45: =(J44-I44)*'2. Control Panel'!$L$20 -> 0 | K45: =(K44-J44)*'2. Control Panel'!$L$20 -> 0 | L45: =(L44-K44)*'2. Control Panel'!$L$20 -> 0 | M45: =(M44-L44)*'2. Control Panel'!$L$20 -> 0
C46: Number of R1 universities with paid subscriptions | D46: =D44-D45 -> 0 | E46: =E44-E45 -> 15 | F46: =IF(E44*(1+F43)>'2. Control Panel'!$L$33,'2. Control Panel'!$L$33,'4.1 Revenue & Cost Breakdown'!E44*(1+'4.1 Revenue & Cost Breakdown'!F43)) -> 45 | G46: =IF(F44*(1+G43)>'2. Control Panel'!$L$33,'2. Control Panel'!$L$33,'4.1 Revenue & Cost Breakdown'!F44*(1+'4.1 Revenue & Cost Breakdown'!G43)) -> 67.5 | H46: =IF(G44*(1+H43)>'2. Control Panel'!$L$33,'2. Control Panel'!$L$33,'4.1 Revenue & Cost Breakdown'!G44*(1+'4.1 Revenue & Cost Breakdown'!H43)) -> 101.25 | I46: =IF(H44*(1+I43)>'2. Control Panel'!$L$33,'2. Control Panel'!$L$33,'4.1 Revenue & Cost Breakdown'!H44*(1+'4.1 Revenue & Cost Breakdown'!I43)) -> 162 | J46: =IF(I44*(1+J43)>'2. Control Panel'!$L$33,'2. Control Panel'!$L$33,'4.1 Revenue & Cost Breakdown'!I44*(1+'4.1 Revenue & Cost Breakdown'!J43)) -> 187 | K46: =IF(J44*(1+K43)>'2. Control Panel'!$L$33,'2. Control Panel'!$L$33,'4.1 Revenue & Cost Breakdown'!J44*(1+'4.1 Revenue & Cost Breakdown'!K43)) -> 187 | L46: =IF(K44*(1+L43)>'2. Control Panel'!$L$33,'2. Control Panel'!$L$33,'4.1 Revenue & Cost Breakdown'!K44*(1+'4.1 Revenue & Cost Breakdown'!L43)) -> 187 | M46: =IF(L44*(1+M43)>'2. Control Panel'!$L$33,'2. Control Panel'!$L$33,'4.1 Revenue & Cost Breakdown'!L44*(1+'4.1 Revenue & Cost Breakdown'!M43)) -> 187
C47: Number of R2 universities with paid subscriptions | E47: {=_xlfn.IFS(E44<='2. Control Panel'!$L$33,0,AND('4.1 Revenue & Cost Breakdown'!E44>'2. Control Panel'!$L$33,'4.1 Revenue & Cost Breakdown'!E44<('2. Control Panel'!$L$33+'2. Control Panel'!$L$34)),'4.1 Revenue & Cost Breakdown'!E44-SUM('4.1 Revenue & Cost Breakdown'!E45:E46),'4.1 Revenue & Cost Breakdown'!E44>('2. Control Panel'!$L$33+'2. Control Panel'!$L$34),'2. Control Panel'!$L$34)} -> 0 | F47: {=_xlfn.IFS(F44<='2. Control Panel'!$L$33,0,AND('4.1 Revenue & Cost Breakdown'!F44>'2. Control Panel'!$L$33,'4.1 Revenue & Cost Breakdown'!F44<('2. Control Panel'!$L$33+'2. Control Panel'!$L$34)),'4.1 Revenue & Cost Breakdown'!F44-SUM('4.1 Revenue & Cost Breakdown'!F45:F46),'4.1 Revenue & Cost Breakdown'!F44>('2. Control Panel'!$L$33+'2. Control Panel'!$L$34),'2. Control Panel'!$L$34)} -> 0 | G47: {=_xlfn.IFS(G44<='2. Control Panel'!$L$33,0,AND('4.1 Revenue & Cost Breakdown'!G44>'2. Control Panel'!$L$33,'4.1 Revenue & Cost Breakdown'!G44<('2. Control Panel'!$L$33+'2. Control Panel'!$L$34)),'4.1 Revenue & Cost Breakdown'!G44-SUM('4.1 Revenue & Cost Breakdown'!G45:G46),'4.1 Revenue & Cost Breakdown'!G44>('2. Control Panel'!$L$33+'2. Control Panel'!$L$34),'2. Control Panel'!$L$34)} -> 0 | H47: {=_xlfn.IFS(H44<='2. Control Panel'!$L$33,0,AND('4.1 Revenue & Cost Breakdown'!H44>'2. Control Panel'!$L$33,'4.1 Revenue & Cost Breakdown'!H44<('2. Control Panel'!$L$33+'2. Control Panel'!$L$34)),'4.1 Revenue & Cost Breakdown'!H44-SUM('4.1 Revenue & Cost Breakdown'!H45:H46),'4.1 Revenue & Cost Breakdown'!H44>('2. Control Panel'!$L$33+'2. Control Panel'!$L$34),'2. Control Panel'!$L$34)} -> 0 | I47: {=_xlfn.IFS(I44<='2. Control Panel'!$L$33,0,AND('4.1 Revenue & Cost Breakdown'!I44>'2. Control Panel'!$L$33,'4.1 Revenue & Cost Breakdown'!I44<('2. Control Panel'!$L$33+'2. Control Panel'!$L$34)),'4.1 Revenue & Cost Breakdown'!I44-SUM('4.1 Revenue & Cost Breakdown'!I45:I46),'4.1 Revenue & Cost Breakdown'!I44>('2. Control Panel'!$L$33+'2. Control Panel'!$L$34),'2. Control Panel'!$L$34)} -> 0 | J47: {=_xlfn.IFS(J44<='2. Control Panel'!$L$33,0,AND('4.1 Revenue & Cost Breakdown'!J44>'2. Control Panel'!$L$33,'4.1 Revenue & Cost Breakdown'!J44<('2. Control Panel'!$L$33+'2. Control Panel'!$L$34)),'4.1 Revenue & Cost Breakdown'!J44-SUM('4.1 Revenue & Cost Breakdown'!J45:J46),'4.1 Revenue & Cost Breakdown'!J44>('2. Control Panel'!$L$33+'2. Control Panel'!$L$34),'2. Control Panel'!$L$34)} -> 72.2 | K47: {=_xlfn.IFS(K44<='2. Control Panel'!$L$33,0,AND('4.1 Revenue & Cost Breakdown'!K44>'2. Control Panel'!$L$33,'4.1 Revenue & Cost Breakdown'!K44<('2. Control Panel'!$L$33+'2. Control Panel'!$L$34)),'4.1 Revenue & Cost Breakdown'!K44-SUM('4.1 Revenue & Cost Breakdown'!K45:K46),'4.1 Revenue & Cost Breakdown'!K44>('2. Control Panel'!$L$33+'2. Control Panel'!$L$34),'2. Control Panel'!$L$34)} -> 139 | L47: {=_xlfn.IFS(L44<='2. Control Panel'!$L$33,0,AND('4.1 Revenue & Cost Breakdown'!L44>'2. Control Panel'!$L$33,'4.1 Revenue & Cost Breakdown'!L44<('2. Control Panel'!$L$33+'2. Control Panel'!$L$34)),'4.1 Revenue & Cost Breakdown'!L44-SUM('4.1 Revenue & Cost Breakdown'!L45:L46),'4.1 Revenue & Cost Breakdown'!L44>('2. Control Panel'!$L$33+'2. Control Panel'!$L$34),'2. Control Panel'!$L$34)} -> 139 | M47: {=_xlfn.IFS(M44<='2. Control Panel'!$L$33,0,AND('4.1 Revenue & Cost Breakdown'!M44>'2. Control Panel'!$L$33,'4.1 Revenue & Cost Breakdown'!M44<('2. Control Panel'!$L$33+'2. Control Panel'!$L$34)),'4.1 Revenue & Cost Breakdown'!M44-SUM('4.1 Revenue & Cost Breakdown'!M45:M46),'4.1 Revenue & Cost Breakdown'!M44>('2. Control Panel'!$L$33+'2. Control Panel'!$L$34),'2. Control Panel'!$L$34)} -> 139
C48: Number of R3 universities with paid subscriptions | E48: {=_xlfn.IFS(E44<=('2. Control Panel'!$L$33+'2. Control Panel'!$L$34),0,AND('4.1 Revenue & Cost Breakdown'!E44>('2. Control Panel'!$L$33+'2. Control Panel'!$L$34),'4.1 Revenue & Cost Breakdown'!E44<('2. Control Panel'!$L$33+'2. Control Panel'!$L$34+'2. Control Panel'!$L$35)),'4.1 Revenue & Cost Breakdown'!E44-SUM('4.1 Revenue & Cost Breakdown'!E45:E47),'4.1 Revenue & Cost Breakdown'!E44>('2. Control Panel'!$L$33+'2. Control Panel'!$L$34+'2. Control Panel'!$L$35),'2. Control Panel'!$L$35)} -> 0 | F48: {=_xlfn.IFS(F44<=('2. Control Panel'!$L$33+'2. Control Panel'!$L$34),0,AND('4.1 Revenue & Cost Breakdown'!F44>('2. Control Panel'!$L$33+'2. Control Panel'!$L$34),'4.1 Revenue & Cost Breakdown'!F44<('2. Control Panel'!$L$33+'2. Control Panel'!$L$34+'2. Control Panel'!$L$35)),'4.1 Revenue & Cost Breakdown'!F44-SUM('4.1 Revenue & Cost Breakdown'!F45:F47),'4.1 Revenue & Cost Breakdown'!F44>('2. Control Panel'!$L$33+'2. Control Panel'!$L$34+'2. Control Panel'!$L$35),'2. Control Panel'!$L$35)} -> 0 | G48: {=_xlfn.IFS(G44<=('2. Control Panel'!$L$33+'2. Control Panel'!$L$34),0,AND('4.1 Revenue & Cost Breakdown'!G44>('2. Control Panel'!$L$33+'2. Control Panel'!$L$34),'4.1 Revenue & Cost Breakdown'!G44<('2. Control Panel'!$L$33+'2. Control Panel'!$L$34+'2. Control Panel'!$L$35)),'4.1 Revenue & Cost Breakdown'!G44-SUM('4.1 Revenue & Cost Breakdown'!G45:G47),'4.1 Revenue & Cost Breakdown'!G44>('2. Control Panel'!$L$33+'2. Control Panel'!$L$34+'2. Control Panel'!$L$35),'2. Control Panel'!$L$35)} -> 0 | H48: {=_xlfn.IFS(H44<=('2. Control Panel'!$L$33+'2. Control Panel'!$L$34),0,AND('4.1 Revenue & Cost Breakdown'!H44>('2. Control Panel'!$L$33+'2. Control Panel'!$L$34),'4.1 Revenue & Cost Breakdown'!H44<('2. Control Panel'!$L$33+'2. Control Panel'!$L$34+'2. Control Panel'!$L$35)),'4.1 Revenue & Cost Breakdown'!H44-SUM('4.1 Revenue & Cost Breakdown'!H45:H47),'4.1 Revenue & Cost Breakdown'!H44>('2. Control Panel'!$L$33+'2. Control Panel'!$L$34+'2. Control Panel'!$L$35),'2. Control Panel'!$L$35)} -> 0 | I48: {=_xlfn.IFS(I44<=('2. Control Panel'!$L$33+'2. Control Panel'!$L$34),0,AND('4.1 Revenue & Cost Breakdown'!I44>('2. Control Panel'!$L$33+'2. Control Panel'!$L$34),'4.1 Revenue & Cost Breakdown'!I44<('2. Control Panel'!$L$33+'2. Control Panel'!$L$34+'2. Control Panel'!$L$35)),'4.1 Revenue & Cost Breakdown'!I44-SUM('4.1 Revenue & Cost Breakdown'!I45:I47),'4.1 Revenue & Cost Breakdown'!I44>('2. Control Panel'!$L$33+'2. Control Panel'!$L$34+'2. Control Panel'!$L$35),'2. Control Panel'!$L$35)} -> 0 | J48: {=_xlfn.IFS(J44<=('2. Control Panel'!$L$33+'2. Control Panel'!$L$34),0,AND('4.1 Revenue & Cost Breakdown'!J44>('2. Control Panel'!$L$33+'2. Control Panel'!$L$34),'4.1 Revenue & Cost Breakdown'!J44<('2. Control Panel'!$L$33+'2. Control Panel'!$L$34+'2. Control Panel'!$L$35)),'4.1 Revenue & Cost Breakdown'!J44-SUM('4.1 Revenue & Cost Breakdown'!J45:J47),'4.1 Revenue & Cost Breakdown'!J44>('2. Control Panel'!$L$33+'2. Control Panel'!$L$34+'2. Control Panel'!$L$35),'2. Control Panel'!$L$35)} -> 0 | K48: {=_xlfn.IFS(K44<=('2. Control Panel'!$L$33+'2. Control Panel'!$L$34),0,AND('4.1 Revenue & Cost Breakdown'!K44>('2. Control Panel'!$L$33+'2. Control Panel'!$L$34),'4.1 Revenue & Cost Breakdown'!K44<('2. Control Panel'!$L$33+'2. Control Panel'!$L$34+'2. Control Panel'!$L$35)),'4.1 Revenue & Cost Breakdown'!K44-SUM('4.1 Revenue & Cost Breakdown'!K45:K47),'4.1 Revenue & Cost Breakdown'!K44>('2. Control Panel'!$L$33+'2. Control Panel'!$L$34+'2. Control Panel'!$L$35),'2. Control Panel'!$L$35)} -> 88.72 | L48: {=_xlfn.IFS(L44<=('2. Control Panel'!$L$33+'2. Control Panel'!$L$34),0,AND('4.1 Revenue & Cost Breakdown'!L44>('2. Control Panel'!$L$33+'2. Control Panel'!$L$34),'4.1 Revenue & Cost Breakdown'!L44<('2. Control Panel'!$L$33+'2. Control Panel'!$L$34+'2. Control Panel'!$L$35)),'4.1 Revenue & Cost Breakdown'!L44-SUM('4.1 Revenue & Cost Breakdown'!L45:L47),'4.1 Revenue & Cost Breakdown'!L44>('2. Control Panel'!$L$33+'2. Control Panel'!$L$34+'2. Control Panel'!$L$35),'2. Control Panel'!$L$35)} -> 189 | M48: {=_xlfn.IFS(M44<=('2. Control Panel'!$L$33+'2. Control Panel'!$L$34),0,AND('4.1 Revenue & Cost Breakdown'!M44>('2. Control Panel'!$L$33+'2. Control Panel'!$L$34),'4.1 Revenue & Cost Breakdown'!M44<('2. Control Panel'!$L$33+'2. Control Panel'!$L$34+'2. Control Panel'!$L$35)),'4.1 Revenue & Cost Breakdown'!M44-SUM('4.1 Revenue & Cost Breakdown'!M45:M47),'4.1 Revenue & Cost Breakdown'!M44>('2. Control Panel'!$L$33+'2. Control Panel'!$L$34+'2. Control Panel'!$L$35),'2. Control Panel'!$L$35)} -> 189
C49: Number of other U.S. universities with paid subscriptions | E49: {=_xlfn.IFS(E44<=('2. Control Panel'!$L$33+'2. Control Panel'!$L$34+'2. Control Panel'!$L$35),0,AND('4.1 Revenue & Cost Breakdown'!E44>('2. Control Panel'!$L$33+'2. Control Panel'!$L$34+'2. Control Panel'!$L$35),'4.1 Revenue & Cost Breakdown'!E44<('2. Control Panel'!$L$33+'2. Control Panel'!$L$34+'2. Control Panel'!$L$35+'2. Control Panel'!$L$36)),'4.1 Revenue & Cost Breakdown'!E44-SUM('4.1 Revenue & Cost Breakdown'!E45:E48),'4.1 Revenue & Cost Breakdown'!E44>('2. Control Panel'!$L$33+'2. Control Panel'!$L$34+'2. Control Panel'!$L$35+'2. Control Panel'!$L$36),'2. Control Panel'!$L$36)} -> 0 | F49: {=_xlfn.IFS(F44<=('2. Control Panel'!$L$33+'2. Control Panel'!$L$34+'2. Control Panel'!$L$35),0,AND('4.1 Revenue & Cost Breakdown'!F44>('2. Control Panel'!$L$33+'2. Control Panel'!$L$34+'2. Control Panel'!$L$35),'4.1 Revenue & Cost Breakdown'!F44<('2. Control Panel'!$L$33+'2. Control Panel'!$L$34+'2. Control Panel'!$L$35+'2. Control Panel'!$L$36)),'4.1 Revenue & Cost Breakdown'!F44-SUM('4.1 Revenue & Cost Breakdown'!F45:F48),'4.1 Revenue & Cost Breakdown'!F44>('2. Control Panel'!$L$33+'2. Control Panel'!$L$34+'2. Control Panel'!$L$35+'2. Control Panel'!$L$36),'2. Control Panel'!$L$36)} -> 0 | G49: {=_xlfn.IFS(G44<=('2. Control Panel'!$L$33+'2. Control Panel'!$L$34+'2. Control Panel'!$L$35),0,AND('4.1 Revenue & Cost Breakdown'!G44>('2. Control Panel'!$L$33+'2. Control Panel'!$L$34+'2. Control Panel'!$L$35),'4.1 Revenue & Cost Breakdown'!G44<('2. Control Panel'!$L$33+'2. Control Panel'!$L$34+'2. Control Panel'!$L$35+'2. Control Panel'!$L$36)),'4.1 Revenue & Cost Breakdown'!G44-SUM('4.1 Revenue & Cost Breakdown'!G45:G48),'4.1 Revenue & Cost Breakdown'!G44>('2. Control Panel'!$L$33+'2. Control Panel'!$L$34+'2. Control Panel'!$L$35+'2. Control Panel'!$L$36),'2. Control Panel'!$L$36)} -> 0 | H49: {=_xlfn.IFS(H44<=('2. Control Panel'!$L$33+'2. Control Panel'!$L$34+'2. Control Panel'!$L$35),0,AND('4.1 Revenue & Cost Breakdown'!H44>('2. Control Panel'!$L$33+'2. Control Panel'!$L$34+'2. Control Panel'!$L$35),'4.1 Revenue & Cost Breakdown'!H44<('2. Control Panel'!$L$33+'2. Control Panel'!$L$34+'2. Control Panel'!$L$35+'2. Control Panel'!$L$36)),'4.1 Revenue & Cost Breakdown'!H44-SUM('4.1 Revenue & Cost Breakdown'!H45:H48),'4.1 Revenue & Cost Breakdown'!H44>('2. Control Panel'!$L$33+'2. Control Panel'!$L$34+'2. Control Panel'!$L$35+'2. Control Panel'!$L$36),'2. Control Panel'!$L$36)} -> 0 | I49: {=_xlfn.IFS(I44<=('2. Control Panel'!$L$33+'2. Control Panel'!$L$34+'2. Control Panel'!$L$35),0,AND('4.1 Revenue & Cost Breakdown'!I44>('2. Control Panel'!$L$33+'2. Control Panel'!$L$34+'2. Control Panel'!$L$35),'4.1 Revenue & Cost Breakdown'!I44<('2. Control Panel'!$L$33+'2. Control Panel'!$L$34+'2. Control Panel'!$L$35+'2. Control Panel'!$L$36)),'4.1 Revenue & Cost Breakdown'!I44-SUM('4.1 Revenue & Cost Breakdown'!I45:I48),'4.1 Revenue & Cost Breakdown'!I44>('2. Control Panel'!$L$33+'2. Control Panel'!$L$34+'2. Control Panel'!$L$35+'2. Control Panel'!$L$36),'2. Control Panel'!$L$36)} -> 0 | J49: {=_xlfn.IFS(J44<=('2. Control Panel'!$L$33+'2. Control Panel'!$L$34+'2. Control Panel'!$L$35),0,AND('4.1 Revenue & Cost Breakdown'!J44>('2. Control Panel'!$L$33+'2. Control Panel'!$L$34+'2. Control Panel'!$L$35),'4.1 Revenue & Cost Breakdown'!J44<('2. Control Panel'!$L$33+'2. Control Panel'!$L$34+'2. Control Panel'!$L$35+'2. Control Panel'!$L$36)),'4.1 Revenue & Cost Breakdown'!J44-SUM('4.1 Revenue & Cost Breakdown'!J45:J48),'4.1 Revenue & Cost Breakdown'!J44>('2. Control Panel'!$L$33+'2. Control Panel'!$L$34+'2. Control Panel'!$L$35+'2. Control Panel'!$L$36),'2. Control Panel'!$L$36)} -> 0 | K49: {=_xlfn.IFS(K44<=('2. Control Panel'!$L$33+'2. Control Panel'!$L$34+'2. Control Panel'!$L$35),0,AND('4.1 Revenue & Cost Breakdown'!K44>('2. Control Panel'!$L$33+'2. Control Panel'!$L$34+'2. Control Panel'!$L$35),'4.1 Revenue & Cost Breakdown'!K44<('2. Control Panel'!$L$33+'2. Control Panel'!$L$34+'2. Control Panel'!$L$35+'2. Control Panel'!$L$36)),'4.1 Revenue & Cost Breakdown'!K44-SUM('4.1 Revenue & Cost Breakdown'!K45:K48),'4.1 Revenue & Cost Breakdown'!K44>('2. Control Panel'!$L$33+'2. Control Panel'!$L$34+'2. Control Panel'!$L$35+'2. Control Panel'!$L$36),'2. Control Panel'!$L$36)} -> 0 | L49: {=_xlfn.IFS(L44<=('2. Control Panel'!$L$33+'2. Control Panel'!$L$34+'2. Control Panel'!$L$35),0,AND('4.1 Revenue & Cost Breakdown'!L44>('2. Control Panel'!$L$33+'2. Control Panel'!$L$34+'2. Control Panel'!$L$35),'4.1 Revenue & Cost Breakdown'!L44<('2. Control Panel'!$L$33+'2. Control Panel'!$L$34+'2. Control Panel'!$L$35+'2. Control Panel'!$L$36)),'4.1 Revenue & Cost Breakdown'!L44-SUM('4.1 Revenue & Cost Breakdown'!L45:L48),'4.1 Revenue & Cost Breakdown'!L44>('2. Control Panel'!$L$33+'2. Control Panel'!$L$34+'2. Control Panel'!$L$35+'2. Control Panel'!$L$36),'2. Control Panel'!$L$36)} -> 107.08 | M49: {=_xlfn.IFS(M44<=('2. Control Panel'!$L$33+'2. Control Panel'!$L$34+'2. Control Panel'!$L$35),0,AND('4.1 Revenue & Cost Breakdown'!M44>('2. Control Panel'!$L$33+'2. Control Panel'!$L$34+'2. Control Panel'!$L$35),'4.1 Revenue & Cost Breakdown'!M44<('2. Control Panel'!$L$33+'2. Control Panel'!$L$34+'2. Control Panel'!$L$35+'2. Control Panel'!$L$36)),'4.1 Revenue & Cost Breakdown'!M44-SUM('4.1 Revenue & Cost Breakdown'!M45:M48),'4.1 Revenue & Cost Breakdown'!M44>('2. Control Panel'!$L$33+'2. Control Panel'!$L$34+'2. Control Panel'!$L$35+'2. Control Panel'!$L$36),'2. Control Panel'!$L$36)} -> 418.12
C50: Number of other global universities with paid subscriptions | E50: {=_xlfn.IFS(E44<=('2. Control Panel'!$L$33+'2. Control Panel'!$L$34+'2. Control Panel'!$L$35+'2. Control Panel'!$L$36),0,AND('4.1 Revenue & Cost Breakdown'!E44>('2. Control Panel'!$L$33+'2. Control Panel'!$L$34+'2. Control Panel'!$L$35+'2. Control Panel'!$L$36),'4.1 Revenue & Cost Breakdown'!E44<('2. Control Panel'!$L$33+'2. Control Panel'!$L$34+'2. Control Panel'!$L$35+'2. Control Panel'!$L$36+'2. Control Panel'!$L$37)),'4.1 Revenue & Cost Breakdown'!E44-SUM('4.1 Revenue & Cost Breakdown'!E45:E49),'4.1 Revenue & Cost Breakdown'!E44>('2. Control Panel'!$L$33+'2. Control Panel'!$L$34+'2. Control Panel'!$L$35+'2. Control Panel'!$L$36+'2. Control Panel'!$L$37),'2. Control Panel'!$L$37)} -> 0 | F50: {=_xlfn.IFS(F44<=('2. Control Panel'!$L$33+'2. Control Panel'!$L$34+'2. Control Panel'!$L$35+'2. Control Panel'!$L$36),0,AND('4.1 Revenue & Cost Breakdown'!F44>('2. Control Panel'!$L$33+'2. Control Panel'!$L$34+'2. Control Panel'!$L$35+'2. Control Panel'!$L$36),'4.1 Revenue & Cost Breakdown'!F44<('2. Control Panel'!$L$33+'2. Control Panel'!$L$34+'2. Control Panel'!$L$35+'2. Control Panel'!$L$36+'2. Control Panel'!$L$37)),'4.1 Revenue & Cost Breakdown'!F44-SUM('4.1 Revenue & Cost Breakdown'!F45:F49),'4.1 Revenue & Cost Breakdown'!F44>('2. Control Panel'!$L$33+'2. Control Panel'!$L$34+'2. Control Panel'!$L$35+'2. Control Panel'!$L$36+'2. Control Panel'!$L$37),'2. Control Panel'!$L$37)} -> 0 | G50: {=_xlfn.IFS(G44<=('2. Control Panel'!$L$33+'2. Control Panel'!$L$34+'2. Control Panel'!$L$35+'2. Control Panel'!$L$36),0,AND('4.1 Revenue & Cost Breakdown'!G44>('2. Control Panel'!$L$33+'2. Control Panel'!$L$34+'2. Control Panel'!$L$35+'2. Control Panel'!$L$36),'4.1 Revenue & Cost Breakdown'!G44<('2. Control Panel'!$L$33+'2. Control Panel'!$L$34+'2. Control Panel'!$L$35+'2. Control Panel'!$L$36+'2. Control Panel'!$L$37)),'4.1 Revenue & Cost Breakdown'!G44-SUM('4.1 Revenue & Cost Breakdown'!G45:G49),'4.1 Revenue & Cost Breakdown'!G44>('2. Control Panel'!$L$33+'2. Control Panel'!$L$34+'2. Control Panel'!$L$35+'2. Control Panel'!$L$36+'2. Control Panel'!$L$37),'2. Control Panel'!$L$37)} -> 0 | H50: {=_xlfn.IFS(H44<=('2. Control Panel'!$L$33+'2. Control Panel'!$L$34+'2. Control Panel'!$L$35+'2. Control Panel'!$L$36),0,AND('4.1 Revenue & Cost Breakdown'!H44>('2. Control Panel'!$L$33+'2. Control Panel'!$L$34+'2. Control Panel'!$L$35+'2. Control Panel'!$L$36),'4.1 Revenue & Cost Breakdown'!H44<('2. Control Panel'!$L$33+'2. Control Panel'!$L$34+'2. Control Panel'!$L$35+'2. Control Panel'!$L$36+'2. Control Panel'!$L$37)),'4.1 Revenue & Cost Breakdown'!H44-SUM('4.1 Revenue & Cost Breakdown'!H45:H49),'4.1 Revenue & Cost Breakdown'!H44>('2. Control Panel'!$L$33+'2. Control Panel'!$L$34+'2. Control Panel'!$L$35+'2. Control Panel'!$L$36+'2. Control Panel'!$L$37),'2. Control Panel'!$L$37)} -> 0 | I50: {=_xlfn.IFS(I44<=('2. Control Panel'!$L$33+'2. Control Panel'!$L$34+'2. Control Panel'!$L$35+'2. Control Panel'!$L$36),0,AND('4.1 Revenue & Cost Breakdown'!I44>('2. Control Panel'!$L$33+'2. Control Panel'!$L$34+'2. Control Panel'!$L$35+'2. Control Panel'!$L$36),'4.1 Revenue & Cost Breakdown'!I44<('2. Control Panel'!$L$33+'2. Control Panel'!$L$34+'2. Control Panel'!$L$35+'2. Control Panel'!$L$36+'2. Control Panel'!$L$37)),'4.1 Revenue & Cost Breakdown'!I44-SUM('4.1 Revenue & Cost Breakdown'!I45:I49),'4.1 Revenue & Cost Breakdown'!I44>('2. Control Panel'!$L$33+'2. Control Panel'!$L$34+'2. Control Panel'!$L$35+'2. Control Panel'!$L$36+'2. Control Panel'!$L$37),'2. Control Panel'!$L$37)} -> 0 | J50: {=_xlfn.IFS(J44<=('2. Control Panel'!$L$33+'2. Control Panel'!$L$34+'2. Control Panel'!$L$35+'2. Control Panel'!$L$36),0,AND('4.1 Revenue & Cost Breakdown'!J44>('2. Control Panel'!$L$33+'2. Control Panel'!$L$34+'2. Control Panel'!$L$35+'2. Control Panel'!$L$36),'4.1 Revenue & Cost Breakdown'!J44<('2. Control Panel'!$L$33+'2. Control Panel'!$L$34+'2. Control Panel'!$L$35+'2. Control Panel'!$L$36+'2. Control Panel'!$L$37)),'4.1 Revenue & Cost Breakdown'!J44-SUM('4.1 Revenue & Cost Breakdown'!J45:J49),'4.1 Revenue & Cost Breakdown'!J44>('2. Control Panel'!$L$33+'2. Control Panel'!$L$34+'2. Control Panel'!$L$35+'2. Control Panel'!$L$36+'2. Control Panel'!$L$37),'2. Control Panel'!$L$37)} -> 0 | K50: {=_xlfn.IFS(K44<=('2. Control Panel'!$L$33+'2. Control Panel'!$L$34+'2. Control Panel'!$L$35+'2. Control Panel'!$L$36),0,AND('4.1 Revenue & Cost Breakdown'!K44>('2. Control Panel'!$L$33+'2. Control Panel'!$L$34+'2. Control Panel'!$L$35+'2. Control Panel'!$L$36),'4.1 Revenue & Cost Breakdown'!K44<('2. Control Panel'!$L$33+'2. Control Panel'!$L$34+'2. Control Panel'!$L$35+'2. Control Panel'!$L$36+'2. Control Panel'!$L$37)),'4.1 Revenue & Cost Breakdown'!K44-SUM('4.1 Revenue & Cost Breakdown'!K45:K49),'4.1 Revenue & Cost Breakdown'!K44>('2. Control Panel'!$L$33+'2. Control Panel'!$L$34+'2. Control Panel'!$L$35+'2. Control Panel'!$L$36+'2. Control Panel'!$L$37),'2. Control Panel'!$L$37)} -> 0 | L50: {=_xlfn.IFS(L44<=('2. Control Panel'!$L$33+'2. Control Panel'!$L$34+'2. Control Panel'!$L$35+'2. Control Panel'!$L$36),0,AND('4.1 Revenue & Cost Breakdown'!L44>('2. Control Panel'!$L$33+'2. Control Panel'!$L$34+'2. Control Panel'!$L$35+'2. Control Panel'!$L$36),'4.1 Revenue & Cost Breakdown'!L44<('2. Control Panel'!$L$33+'2. Control Panel'!$L$34+'2. Control Panel'!$L$35+'2. Control Panel'!$L$36+'2. Control Panel'!$L$37)),'4.1 Revenue & Cost Breakdown'!L44-SUM('4.1 Revenue & Cost Breakdown'!L45:L49),'4.1 Revenue & Cost Breakdown'!L44>('2. Control Panel'!$L$33+'2. Control Panel'!$L$34+'2. Control Panel'!$L$35+'2. Control Panel'!$L$36+'2. Control Panel'!$L$37),'2. Control Panel'!$L$37)} -> 0 | M50: {=_xlfn.IFS(M44<=('2. Control Panel'!$L$33+'2. Control Panel'!$L$34+'2. Control Panel'!$L$35+'2. Control Panel'!$L$36),0,AND('4.1 Revenue & Cost Breakdown'!M44>('2. Control Panel'!$L$33+'2. Control Panel'!$L$34+'2. Control Panel'!$L$35+'2. Control Panel'!$L$36),'4.1 Revenue & Cost Breakdown'!M44<('2. Control Panel'!$L$33+'2. Control Panel'!$L$34+'2. Control Panel'!$L$35+'2. Control Panel'!$L$36+'2. Control Panel'!$L$37)),'4.1 Revenue & Cost Breakdown'!M44-SUM('4.1 Revenue & Cost Breakdown'!M45:M49),'4.1 Revenue & Cost Breakdown'!M44>('2. Control Panel'!$L$33+'2. Control Panel'!$L$34+'2. Control Panel'!$L$35+'2. Control Panel'!$L$36+'2. Control Panel'!$L$37),'2. Control Panel'!$L$37)} -> 0
C51: % increase in price | D51: ='2. Control Panel'!$L$31 -> 0 | E51: ='2. Control Panel'!$L$31 -> 0 | F51: ='2. Control Panel'!$L$31 -> 0 | G51: ='2. Control Panel'!$L$32 -> 0.05 | H51: ='2. Control Panel'!$L$32 -> 0.05 | I51: ='2. Control Panel'!$L$32 -> 0.05 | J51: ='2. Control Panel'!$L$32 -> 0.05 | K51: ='2. Control Panel'!$L$32 -> 0.05 | L51: ='2. Control Panel'!$L$32 -> 0.05 | M51: ='2. Control Panel'!$L$32 -> 0.05
C52: Spend per R1 university on paid subscriptions | D52: ='2. Control Panel'!$L26*(1+$D$51) -> 200000 | E52: ='2. Control Panel'!$L26*(1+$D$51) -> 200000 | F52: ='2. Control Panel'!$L26*(1+$D$51) -> 200000 | G52: =F52*(1+G$51) -> 210000 | H52: =G52*(1+H51) -> 220500 | I52: =H52*(1+I51) -> 231525 | J52: =I52*(1+J51) -> 243101.25 | K52: =J52*(1+K51) -> 255256.31 | L52: =K52*(1+L51) -> 268019.13 | M52: =L52*(1+M51) -> 281420.08
C53: Spend per R2 university on paid subscriptions | D53: ='2. Control Panel'!$L27*(1+$D$51) -> 180000 | E53: ='2. Control Panel'!$L27*(1+$D$51) -> 180000 | F53: ='2. Control Panel'!$L27*(1+$D$51) -> 180000 | G53: =F53*(1+G$51) -> 189000 | H53: =G53*(1+H$51) -> 198450 | I53: =H53*(1+I$51) -> 208372.5 | J53: =I53*(1+J$51) -> 218791.12 | K53: =J53*(1+K$51) -> 229730.68 | L53: =K53*(1+L$51) -> 241217.22 | M53: =L53*(1+M$51) -> 253278.08
C54: Spend per R3 university on paid subscriptions | D54: ='2. Control Panel'!$L28*(1+$D$51) -> 160000 | E54: ='2. Control Panel'!$L28*(1+$D$51) -> 160000 | F54: ='2. Control Panel'!$L28*(1+$D$51) -> 160000 | G54: =F54*(1+G$51) -> 168000 | H54: =G54*(1+H$51) -> 176400 | I54: =H54*(1+I$51) -> 185220 | J54: =I54*(1+J$51) -> 194481 | K54: =J54*(1+K$51) -> 204205.05 | L54: =K54*(1+L$51) -> 214415.3 | M54: =L54*(1+M$51) -> 225136.07
C55: Spend per other U.S. university on paid subscriptions | D55: ='2. Control Panel'!$L29*(1+$D$51) -> 140000 | E55: ='2. Control Panel'!$L29*(1+$D$51) -> 140000 | F55: ='2. Control Panel'!$L29*(1+$D$51) -> 140000 | G55: =F55*(1+G$51) -> 147000 | H55: =G55*(1+H$51) -> 154350 | I55: =H55*(1+I$51) -> 162067.5 | J55: =I55*(1+J$51) -> 170170.88 | K55: =J55*(1+K$51) -> 178679.42 | L55: =K55*(1+L$51) -> 187613.39 | M55: =L55*(1+M$51) -> 196994.06
C56: Spend per other global university on paid subscriptions | D56: ='2. Control Panel'!$L30*(1+$D$51) -> 120000 | E56: ='2. Control Panel'!$L30*(1+$D$51) -> 120000 | F56: ='2. Control Panel'!$L30*(1+$D$51) -> 120000 | G56: =F56*(1+G$51) -> 126000 | H56: =G56*(1+H$51) -> 132300 | I56: =H56*(1+I$51) -> 138915 | J56: =I56*(1+J$51) -> 145860.75 | K56: =J56*(1+K$51) -> 153153.79 | L56: =K56*(1+L$51) -> 160811.48 | M56: =L56*(1+M$51) -> 168852.05
C57: Revenues | D57: =(D46*D52)+(D47*D53)+(D48*D54)+(D49*D55)+(D50*D56) -> 0 | E57: =(E46*E52)+(E47*E53)+(E48*E54)+(E49*E55)+(E50*E56) -> 3000000 | F57: =(F46*F52)+(F47*F53)+(F48*F54)+(F49*F55)+(F50*F56) -> 9000000 | G57: =(G46*G52)+(G47*G53)+(G48*G54)+(G49*G55)+(G50*G56) -> 14175000 | H57: =(H46*H52)+(H47*H53)+(H48*H54)+(H49*H55)+(H50*H56) -> 22325625 | I57: =(I46*I52)+(I47*I53)+(I48*I54)+(I49*I55)+(I50*I56) -> 37507050 | J57: =(J46*J52)+(J47*J53)+(J48*J54)+(J49*J55)+(J50*J56) -> 61256653 | K57: =(K46*K52)+(K47*K53)+(K48*K54)+(K49*K55)+(K50*K56) -> 97782567 | ... M57: =(M46*M52)+(M47*M53)+(M48*M54)+(M49*M55)+(M50*M56) -> 2.1274908e+08
C60: User 2 - Think Tanks/Non-Profits
D62: 2026 | E62: 2027 | F62: 2028 | G62: 2029 | H62: 2030 | I62: 2031 | J62: 2032 | K62: 2033 | L62: 2034 | M62: 2035
C63: % growth in users with subscriptions | D63: N/A | E63: ='2. Control Panel'!$L$12 -> 0.1 | F63: ='2. Control Panel'!$L$12 -> 0.1 | G63: ='2. Control Panel'!$L$12 -> 0.1 | H63: ='2. Control Panel'!$L$12 -> 0.1 | I63: ='2. Control Panel'!$L$12 -> 0.1 | J63: ='2. Control Panel'!$L$12 -> 0.1 | K63: ='2. Control Panel'!$L$12 -> 0.1 | L63: ='2. Control Panel'!$L$12 -> 0.1 | M63: ='2. Control Panel'!$L$12 -> 0.1
C64: Number of think tanks/non-profits with subscriptions | D64: ='2. Control Panel'!$L$38 -> 0 | E64: =D64*(1+E63) -> 0 | F64: =E64*(1+F63) -> 0 | G64: =F64*(1+G63) -> 0 | H64: =G64*(1+H63) -> 0 | I64: =IF($H64=0,'2. Control Panel'!L39,H64*(1+I63)) -> 3000 | J64: =I64*(1+J63) -> 3300 | K64: =J64*(1+K63) -> 3630 | L64: =K64*(1+L63) -> 3993 | M64: =L64*(1+M63) -> 4392.3
C65: % increase in price | D65: ='2. Control Panel'!$L$13 -> 0 | E65: ='2. Control Panel'!$L$13 -> 0 | F65: ='2. Control Panel'!$L$13 -> 0 | G65: ='2. Control Panel'!$L$14 -> 0.05 | H65: ='2. Control Panel'!$L$14 -> 0.05 | I65: ='2. Control Panel'!$L$14 -> 0.05 | J65: ='2. Control Panel'!$L$14 -> 0.05 | K65: ='2. Control Panel'!$L$14 -> 0.05 | L65: ='2. Control Panel'!$L$14 -> 0.05 | M65: ='2. Control Panel'!$L$14 -> 0.05
C66: Spend per think tank/non-profit on subscriptions | D66: ='2. Control Panel'!L40 -> 50000 | E66: =D66*(1+E65) -> 50000 | F66: =E66*(1+F65) -> 50000 | G66: =F66*(1+G65) -> 52500 | H66: =G66*(1+H65) -> 55125 | I66: =H66*(1+I65) -> 57881.25 | J66: =I66*(1+J65) -> 60775.312 | K66: =J66*(1+K65) -> 63814.078 | L66: =K66*(1+L65) -> 67004.782 | M66: =L66*(1+M65) -> 70355.021
C67: Revenues | D67: =D64*D66 -> 0 | E67: =E64*E66 -> 0 | F67: =F64*F66 -> 0 | G67: =G64*G66 -> 0 | H67: =H64*H66 -> 0 | I67: =I64*I66 -> 173643750 | J67: =J64*J66 -> 2.0055853e+08 | K67: =K64*K66 -> 2.316451e+08 | ... M67: =M64*M66 -> 3.0902036e+08
C70: User 3 - Government Organization
D72: 2026 | E72: 2027 | F72: 2028 | G72: 2029 | H72: 2030 | I72: 2031 | J72: 2032 | K72: 2033 | L72: 2034 | M72: 2035
C73: % growth in users with subscriptions | D73: N/A | E73: ='2. Control Panel'!$L$12 -> 0.1 | F73: ='2. Control Panel'!$L$12 -> 0.1 | G73: ='2. Control Panel'!$L$12 -> 0.1 | H73: ='2. Control Panel'!$L$12 -> 0.1 | I73: ='2. Control Panel'!$L$12 -> 0.1 | J73: ='2. Control Panel'!$L$12 -> 0.1 | K73: ='2. Control Panel'!$L$12 -> 0.1 | L73: ='2. Control Panel'!$L$12 -> 0.1 | M73: ='2. Control Panel'!$L$12 -> 0.1
C74: Number of government bodies with subscriptions | D74: ='2. Control Panel'!$L$41 -> 0 | E74: =D74*(1+E73) -> 0 | F74: =E74*(1+F73) -> 0 | G74: =F74*(1+G73) -> 0 | H74: =G74*(1+H73) -> 0 | I74: =IF($H64=0,'2. Control Panel'!L42,H74*(1+I73)) -> 500 | J74: =I74*(1+J73) -> 550 | K74: =J74*(1+K73) -> 605 | L74: =K74*(1+L73) -> 665.5 | M74: =L74*(1+M73) -> 732.05
C75: % increase in price | D75: ='2. Control Panel'!$L$13 -> 0 | E75: ='2. Control Panel'!$L$13 -> 0 | F75: ='2. Control Panel'!$L$13 -> 0 | G75: ='2. Control Panel'!$L$14 -> 0.05 | H75: ='2. Control Panel'!$L$14 -> 0.05 | I75: ='2. Control Panel'!$L$14 -> 0.05 | J75: ='2. Control Panel'!$L$14 -> 0.05 | K75: ='2. Control Panel'!$L$14 -> 0.05 | L75: ='2. Control Panel'!$L$14 -> 0.05 | M75: ='2. Control Panel'!$L$14 -> 0.05
C76: Spend per government body on subscriptions | D76: ='2. Control Panel'!L43 -> 50000 | E76: =D76*(1+E75) -> 50000 | F76: =E76*(1+F75) -> 50000 | G76: =F76*(1+G75) -> 52500 | H76: =G76*(1+H75) -> 55125 | I76: =H76*(1+I75) -> 57881.25 | J76: =I76*(1+J75) -> 60775.312 | K76: =J76*(1+K75) -> 63814.078 | L76: =K76*(1+L75) -> 67004.782 | M76: =L76*(1+M75) -> 70355.021
C77: Revenues | D77: =D74*D76 -> 0 | E77: =E74*E76 -> 0 | F77: =F74*F76 -> 0 | G77: =G74*G76 -> 0 | H77: =H74*H76 -> 0 | I77: =I74*I76 -> 28940625 | J77: =J74*J76 -> 33426422 | K77: =K74*K76 -> 38607517 | ... M77: =M74*M76 -> 51503393
C80: User 4 - Corporations
D82: 2026 | E82: 2027 | F82: 2028 | G82: 2029 | H82: 2030 | I82: 2031 | J82: 2032 | K82: 2033 | L82: 2034 | M82: 2035
C83: % growth in users with subscriptions | D83: N/A | E83: ='2. Control Panel'!$L$12 -> 0.1 | F83: ='2. Control Panel'!$L$12 -> 0.1 | G83: ='2. Control Panel'!$L$12 -> 0.1 | H83: ='2. Control Panel'!$L$12 -> 0.1 | I83: ='2. Control Panel'!$L$12 -> 0.1 | J83: ='2. Control Panel'!$L$12 -> 0.1 | K83: ='2. Control Panel'!$L$12 -> 0.1 | L83: ='2. Control Panel'!$L$12 -> 0.1 | M83: ='2. Control Panel'!$L$12 -> 0.1
C84: Number of corporations with subscriptions | D84: ='2. Control Panel'!$L$44 -> 0 | E84: =D84*(1+E83) -> 0 | F84: =E84*(1+F83) -> 0 | G84: =F84*(1+G83) -> 0 | H84: =G84*(1+H83) -> 0 | I84: =IF($H84=0,'2. Control Panel'!L45,H84*(1+I83)) -> 500 | J84: =I84*(1+J83) -> 550 | K84: =J84*(1+K83) -> 605 | L84: =K84*(1+L83) -> 665.5 | M84: =L84*(1+M83) -> 732.05
C85: % increase in price | D85: ='2. Control Panel'!$L$13 -> 0 | E85: ='2. Control Panel'!$L$13 -> 0 | F85: ='2. Control Panel'!$L$13 -> 0 | G85: ='2. Control Panel'!$L$14 -> 0.05 | H85: ='2. Control Panel'!$L$14 -> 0.05 | I85: ='2. Control Panel'!$L$14 -> 0.05 | J85: ='2. Control Panel'!$L$14 -> 0.05 | K85: ='2. Control Panel'!$L$14 -> 0.05 | L85: ='2. Control Panel'!$L$14 -> 0.05 | M85: ='2. Control Panel'!$L$14 -> 0.05
C86: Spend per corporation on subscriptions | D86: ='2. Control Panel'!L46 -> 100000 | E86: =D86*(1+E85) -> 100000 | F86: =E86*(1+F85) -> 100000 | G86: =F86*(1+G85) -> 105000 | H86: =G86*(1+H85) -> 110250 | I86: =H86*(1+I85) -> 115762.5 | J86: =I86*(1+J85) -> 121550.62 | K86: =J86*(1+K85) -> 127628.16 | L86: =K86*(1+L85) -> 134009.56 | M86: =L86*(1+M85) -> 140710.04
C87: Revenues | D87: =D84*D86 -> 0 | E87: =E84*E86 -> 0 | F87: =F84*F86 -> 0 | G87: =G84*G86 -> 0 | H87: =H84*H86 -> 0 | I87: =I84*I86 -> 57881250 | J87: =J84*J86 -> 66852844 | K87: =K84*K86 -> 77215035 | ... M87: =M84*M86 -> 1.0300679e+08
C90: User 5 - Publishing Organizations
D92: 2026 | E92: 2027 | F92: 2028 | G92: 2029 | H92: 2030 | I92: 2031 | J92: 2032 | K92: 2033 | L92: 2034 | M92: 2035
C93: % growth in users with subscriptions | D93: N/A | E93: ='2. Control Panel'!$L$12 -> 0.1 | F93: ='2. Control Panel'!$L$12 -> 0.1 | G93: ='2. Control Panel'!$L$12 -> 0.1 | H93: ='2. Control Panel'!$L$12 -> 0.1 | I93: ='2. Control Panel'!$L$12 -> 0.1 | J93: ='2. Control Panel'!$L$12 -> 0.1 | K93: ='2. Control Panel'!$L$12 -> 0.1 | L93: ='2. Control Panel'!$L$12 -> 0.1 | M93: ='2. Control Panel'!$L$12 -> 0.1
C94: Number of publishing orgs with subscriptions | D94: ='2. Control Panel'!$L$47 -> 0 | E94: =D94*(1+E93) -> 0 | F94: =E94*(1+F93) -> 0 | G94: =F94*(1+G93) -> 0 | H94: =G94*(1+H93) -> 0 | I94: =IF($H94=0,'2. Control Panel'!L48,H94*(1+I93)) -> 50 | J94: =I94*(1+J93) -> 55 | K94: =J94*(1+K93) -> 60.5 | L94: =K94*(1+L93) -> 66.55 | M94: =L94*(1+M93) -> 73.205
C95: % increase in price | D95: ='2. Control Panel'!$L$13 -> 0 | E95: ='2. Control Panel'!$L$13 -> 0 | F95: ='2. Control Panel'!$L$13 -> 0 | G95: ='2. Control Panel'!$L$14 -> 0.05 | H95: ='2. Control Panel'!$L$14 -> 0.05 | I95: ='2. Control Panel'!$L$14 -> 0.05 | J95: ='2. Control Panel'!$L$14 -> 0.05 | K95: ='2. Control Panel'!$L$14 -> 0.05 | L95: ='2. Control Panel'!$L$14 -> 0.05 | M95: ='2. Control Panel'!$L$14 -> 0.05
C96: Spend per publishing org on subscriptions | D96: ='2. Control Panel'!L49 -> 10000 | E96: =D96*(1+E95) -> 10000 | F96: =E96*(1+F95) -> 10000 | G96: =F96*(1+G95) -> 10500 | H96: =G96*(1+H95) -> 11025 | I96: =H96*(1+I95) -> 11576.25 | J96: =I96*(1+J95) -> 12155.062 | K96: =J96*(1+K95) -> 12762.816 | L96: =K96*(1+L95) -> 13400.956 | M96: =L96*(1+M95) -> 14071.004
C97: Revenues | D97: =D94*D96 -> 0 | E97: =E94*E96 -> 0 | F97: =F94*F96 -> 0 | G97: =G94*G96 -> 0 | H97: =H94*H96 -> 0 | I97: =I94*I96 -> 578812.5 | J97: =J94*J96 -> 668528.44 | K97: =K94*K96 -> 772150.35 | ... M97: =M94*M96 -> 1030067.9
C100: User 6 - Rankings Organizations
D102: 2026 | E102: 2027 | F102: 2028 | G102: 2029 | H102: 2030 | I102: 2031 | J102: 2032 | K102: 2033 | L102: 2034 | M102: 2035
C103: % growth in users with subscriptions | D103: N/A | E103: ='2. Control Panel'!$L$12 -> 0.1 | F103: ='2. Control Panel'!$L$12 -> 0.1 | G103: ='2. Control Panel'!$L$12 -> 0.1 | H103: ='2. Control Panel'!$L$12 -> 0.1 | I103: ='2. Control Panel'!$L$12 -> 0.1 | J103: ='2. Control Panel'!$L$12 -> 0.1 | K103: ='2. Control Panel'!$L$12 -> 0.1 | L103: ='2. Control Panel'!$L$12 -> 0.1 | M103: ='2. Control Panel'!$L$12 -> 0.1
C104: Number of rankings orgs with subscriptions | D104: ='2. Control Panel'!L50 -> 0 | E104: =D104*(1+E103) -> 0 | F104: =E104*(1+F103) -> 0 | G104: =F104*(1+G103) -> 0 | H104: =G104*(1+H103) -> 0 | I104: =IF($H104=0,'2. Control Panel'!L51,H104*(1+I103)) -> 10 | J104: =I104*(1+J103) -> 11 | K104: =J104*(1+K103) -> 12.1 | L104: =K104*(1+L103) -> 13.31 | M104: =L104*(1+M103) -> 14.641
C105: % increase in price | D105: ='2. Control Panel'!$L$13 -> 0 | E105: ='2. Control Panel'!$L$13 -> 0 | F105: ='2. Control Panel'!$L$13 -> 0 | G105: ='2. Control Panel'!$L$14 -> 0.05 | H105: ='2. Control Panel'!$L$14 -> 0.05 | I105: ='2. Control Panel'!$L$14 -> 0.05 | J105: ='2. Control Panel'!$L$14 -> 0.05 | K105: ='2. Control Panel'!$L$14 -> 0.05 | L105: ='2. Control Panel'!$L$14 -> 0.05 | M105: ='2. Control Panel'!$L$14 -> 0.05
C106: Spend per rankings org on subscriptions | D106: ='2. Control Panel'!L52 -> 30000 | E106: =D106*(1+E105) -> 30000 | F106: =E106*(1+F105) -> 30000 | G106: =F106*(1+G105) -> 31500 | H106: =G106*(1+H105) -> 33075 | I106: =H106*(1+I105) -> 34728.75 | J106: =I106*(1+J105) -> 36465.188 | K106: =J106*(1+K105) -> 38288.447 | L106: =K106*(1+L105) -> 40202.869 | M106: =L106*(1+M105) -> 42213.013
C107: Revenues | D107: =D104*D106 -> 0 | E107: =E104*E106 -> 0 | F107: =F104*F106 -> 0 | G107: =G104*G106 -> 0 | H107: =H104*H106 -> 0 | I107: =I104*I106 -> 347287.5 | J107: =J104*J106 -> 401117.06 | K107: =K104*K106 -> 463290.21 | ... M107: =M104*M106 -> 618040.72
C113: Costs
D116: Phase 1 - Seed Development | F116: Phase 2 - Growth | H116: Phase 3 - Scaling
D117: 2026 | E117: 2027 | F117: 2028 | G117: 2029 | H117: 2030 | I117: 2031 | J117: 2032 | K117: 2033 | L117: 2034 | M117: 2035
C118: Operating Expenses (OpEx)
C119: Salaries & Wages: | D119: ='2. Control Panel'!$L$55 -> 0.05 | E119: ='2. Control Panel'!$L$55 -> 0.05 | F119: ='2. Control Panel'!$L$55 -> 0.05 | G119: ='2. Control Panel'!$L$55 -> 0.05 | H119: ='2. Control Panel'!$L$55 -> 0.05 | I119: ='2. Control Panel'!$L$55 -> 0.05 | J119: ='2. Control Panel'!$L$55 -> 0.05 | K119: ='2. Control Panel'!$L$55 -> 0.05 | ... M119: ='2. Control Panel'!$L$55 -> 0.05 | N119: Generic annual % increase of salary/wages (used for SWE + years 1-2 management)
C120: Software engineering | D120: =('2. Control Panel'!L57*'2. Control Panel'!L65)+('2. Control Panel'!L58*'2. Control Panel'!L66)+('2. Control Panel'!L59*'2. Control Panel'!L67)+('2. Control Panel'!L60*'2. Control Panel'!L68)+('2. Control Panel'!L61*'2. Control Panel'!L69)+('2. Control Panel'!L62*'2. Control Panel'!L70) -> 1700000 | E120: =D120*(1+E119) -> 1785000 | F120: =E120+('2. Control Panel'!L76*'2. Control Panel'!L77*(1+SUM(E119:F119))) -> 2247000 | G120: =F120*(1+G119) -> 2359350 | H120: =G120+('2. Control Panel'!L86*'2. Control Panel'!L87*(1+SUM('4.1 Revenue & Cost Breakdown'!E119:H119))) -> 4375350 | I120: =H120*(1+I119) -> 4594117.5 | J120: =I120*(1+J119) -> 4823823.4 | K120: =J120*(1+K119) -> 5065014.5 | L120: =K120*(1+L119) -> 5318265.3 | M120: =L120*(1+M119) -> 5584178.5
C121: Marketing | D121: ='2. Control Panel'!$L$78 -> 0.05 | E121: ='2. Control Panel'!$L$78 -> 0.05 | F121: ='2. Control Panel'!$L$78 -> 0.05 | G121: ='2. Control Panel'!$L$78 -> 0.05 | H121: ='2. Control Panel'!$L$78 -> 0.05 | I121: ='2. Control Panel'!$L$78 -> 0.05 | J121: ='2. Control Panel'!$L$78 -> 0.05 | K121: ='2. Control Panel'!$L$78 -> 0.05 | ... M121: ='2. Control Panel'!$L$78 -> 0.05 | N121: Annual % increase in marketing personnel
D122: ='2. Control Panel'!L63*'2. Control Panel'!L71 -> 180000 | E122: =D122*(1+(E121+E119)) -> 198000 | F122: =E122*(1+(F121+F119)) -> 217800 | G122: =F122*(1+(G121+G119)) -> 239580 | H122: =G122*(1+(H121+H119)) -> 263538 | I122: =H122*(1+(I121+I119)) -> 289891.8 | J122: =I122*(1+(J121+J119)) -> 318880.98 | K122: =J122*(1+(K121+K119)) -> 350769.08 | L122: =K122*(1+(L121+L119)) -> 385845.99 | M122: =L122*(1+(M121+M119)) -> 424430.58
C123: Other business functions (e.g., finance, ops, accounting) | G123: ='2. Control Panel'!$L$81 -> 0.1 | H123: ='2. Control Panel'!$L$81 -> 0.1 | I123: ='2. Control Panel'!$L$81 -> 0.1 | J123: ='2. Control Panel'!$L$81 -> 0.1 | K123: ='2. Control Panel'!$L$81 -> 0.1 | L123: ='2. Control Panel'!$L$81 -> 0.1 | M123: ='2. Control Panel'!$L$81 -> 0.1 | N123: Annual % increase in other business functions personnel
F124: ='2. Control Panel'!L79*'2. Control Panel'!L80 -> 720000 | G124: =F124*(1+G123) -> 792000 | H124: =G124*(1+H123) -> 871200 | I124: =H124*(1+I123) -> 958320 | J124: =I124*(1+J123) -> 1054152 | K124: =J124*(1+K123) -> 1159567.2 | L124: =K124*(1+L123) -> 1275523.9 | M124: =L124*(1+M123) -> 1403076.3
C125: Management | D125: =$D$119 -> 0.05 | E125: =$D$119 -> 0.05 | F125: ='2. Control Panel'!$L$83 -> 0.08 | G125: ='2. Control Panel'!$L$83 -> 0.08 | H125: ='2. Control Panel'!$L$83 -> 0.08 | I125: ='2. Control Panel'!$L$83 -> 0.08 | J125: ='2. Control Panel'!$L$83 -> 0.08 | K125: ='2. Control Panel'!$L$83 -> 0.08 | L125: ='2. Control Panel'!$L$83 -> 0.08 | M125: ='2. Control Panel'!$L$83 -> 0.08
D126: ='2. Control Panel'!L64*'2. Control Panel'!L72 -> 600000 | E126: =D126*(1+E125) -> 630000 | F126: ='2. Control Panel'!L64*'2. Control Panel'!L82 -> 720000 | G126: =F126*(1+G125) -> 777600 | H126: =G126*(1+H125) -> 839808 | I126: =H126*(1+I125) -> 906992.64 | J126: =I126*(1+J125) -> 979552.05 | K126: =J126*(1+K125) -> 1057916.2 | L126: =K126*(1+L125) -> 1142549.5 | M126: =L126*(1+M125) -> 1233953.5
C127: Cloud/Compute costs | D127: ='2. Control Panel'!$L$54 -> 0.1 | E127: ='2. Control Panel'!$L$54 -> 0.1 | F127: ='2. Control Panel'!$L$54 -> 0.1 | G127: ='2. Control Panel'!$L$54 -> 0.1 | H127: ='2. Control Panel'!$L$54 -> 0.1 | I127: ='2. Control Panel'!$L$54 -> 0.1 | J127: ='2. Control Panel'!$L$54 -> 0.1 | K127: ='2. Control Panel'!$L$54 -> 0.1 | ... M127: ='2. Control Panel'!$L$54 -> 0.1 | N127: Annual % increase in of cloud compute costs
D128: ='2. Control Panel'!L73 -> 25000 | E128: =D128*(1+E127) -> 27500 | F128: =E128*(1+F127) -> 30250 | G128: =F128*(1+G127) -> 33275 | H128: =G128*(1+H127) -> 36602.5 | I128: =H128*(1+I127) -> 40262.75 | J128: =I128*(1+J127) -> 44289.025 | K128: =J128*(1+K127) -> 48717.927 | L128: =K128*(1+L127) -> 53589.72 | M128: =L128*(1+M127) -> 58948.692
C129: Marketing/Outreach costs | D129: ='2. Control Panel'!$L$56 -> 0.1 | E129: ='2. Control Panel'!$L$56 -> 0.1 | F129: ='2. Control Panel'!$L$56 -> 0.1 | G129: ='2. Control Panel'!$L$56 -> 0.1 | H129: ='2. Control Panel'!$L$56 -> 0.1 | I129: ='2. Control Panel'!$L$56 -> 0.1 | J129: ='2. Control Panel'!$L$56 -> 0.1 | K129: ='2. Control Panel'!$L$56 -> 0.1 | ... M129: ='2. Control Panel'!$L$56 -> 0.1 | N129: Annual % increase in of marketing/outreach costs
D130: ='2. Control Panel'!L75 -> 100000 | E130: =D130*(1+E129) -> 110000 | F130: =E130*(1+F129) -> 121000 | G130: =F130*(1+G129) -> 133100 | H130: =G130*(1+H129) -> 146410 | I130: =H130*(1+I129) -> 161051 | J130: =I130*(1+J129) -> 177156.1 | K130: =J130*(1+K129) -> 194871.71 | L130: =K130*(1+L129) -> 214358.88 | M130: =L130*(1+M129) -> 235794.77
C131: SG&A Costs | D131: ='2. Control Panel'!$L$53 -> 0.12 | E131: ='2. Control Panel'!$L$53 -> 0.12 | F131: ='2. Control Panel'!$L$53 -> 0.12 | G131: ='2. Control Panel'!$L$53 -> 0.12 | H131: ='2. Control Panel'!$L$53 -> 0.12 | I131: ='2. Control Panel'!$L$53 -> 0.12 | J131: ='2. Control Panel'!$L$53 -> 0.12 | K131: ='2. Control Panel'!$L$53 -> 0.12 | ... M131: ='2. Control Panel'!$L$53 -> 0.12 | N131: Annual % increase in of SG&A
D132: ='2. Control Panel'!L74 -> 50000 | E132: =D132*(1+E131) -> 56000 | F132: =E132*(1+F131) -> 62720 | G132: =F132*(1+G131) -> 70246.4 | H132: =G132*(1+H131) -> 78675.968 | I132: =H132*(1+I131) -> 88117.084 | J132: =I132*(1+J131) -> 98691.134 | K132: =J132*(1+K131) -> 110534.07 | L132: =K132*(1+L131) -> 123798.16 | M132: =L132*(1+M131) -> 138653.94
C133: AI Training Costs | G133: ='2. Control Panel'!$L$85 -> 0.15 | H133: ='2. Control Panel'!$L$85 -> 0.15 | I133: ='2. Control Panel'!$L$85 -> 0.15 | J133: ='2. Control Panel'!$L$85 -> 0.15 | K133: ='2. Control Panel'!$L$85 -> 0.15 | L133: ='2. Control Panel'!$L$85 -> 0.15 | M133: ='2. Control Panel'!$L$85 -> 0.15 | N133: Annual % increase in of AI training costs
F134: ='2. Control Panel'!L84 -> 25000 | G134: =F134*(1+G133) -> 28750 | H134: =G134*(1+H133) -> 33062.5 | I134: =H134*(1+I133) -> 38021.875 | J134: =I134*(1+J133) -> 43725.156 | K134: =J134*(1+K133) -> 50283.93 | L134: =K134*(1+L133) -> 57826.519 | M134: =L134*(1+M133) -> 66500.497
C135: Capital Expenditures (CapEx)
C136: Office and other expenditures | K136: ='2. Control Panel'!$L$88 -> 500000 | L136: ='2. Control Panel'!$L$88 -> 500000 | M136: ='2. Control Panel'!$L$88 -> 500000
C137: TOTALS | D137: =SUM(D120,D122,D124,D126,D128,D130,D132,D134,D136) -> 2655000 | E137: =SUM(E120,E122,E124,E126,E128,E130,E132,E134,E136) -> 2806500 | F137: =SUM(F120,F122,F124,F126,F128,F130,F132,F134,F136) -> 4143770 | G137: =SUM(G120,G122,G124,G126,G128,G130,G132,G134,G136) -> 4433901.4 | H137: =SUM(H120,H122,H124,H126,H128,H130,H132,H134,H136) -> 6644647 | I137: =SUM(I120,I122,I124,I126,I128,I130,I132,I134,I136) -> 7076774.6 | J137: =SUM(J120,J122,J124,J126,J128,J130,J132,J134,J136) -> 7540269.8 | K137: =SUM(K120,K122,K124,K126,K128,K130,K132,K134,K136) -> 8537674.7 | ... M137: =SUM(M120,M122,M124,M126,M128,M130,M132,M134,M136) -> 9645536.8

Sheet Formatting (IGNORE) -->

Sheet Rev_L1 Drop Down
A1: Revenue
A2: Increase_in_Foot_Traffic
A3: Increase_in_Conversion
A4: Increase_in_Average_Transaction_Value

Sheet Costs_L1 Drop Down
A1: Costs
A2: Store_Renovations
A3: Labor_Changes
A4: Marketing_Costs
A5: Income_Lost_During_Transition
A6: Operating_Costs

Sheet Scenario Planning_Drop Down
A1: Scenario_Toggle
A2: 1_Low
A3: 2_Mid
A4: 3_High
